Workbook

Sheet Epics
A1: Epic ID | B1: Epic Name | C1: Story Count | D1: Cadence Spread | E1: FR Coverage
A2: EP-01 | B2: Inquiry and Client Onboarding | C2: 4 | D2: C1 | E2: FR-01, FR-46, FR-48, FR-51, FR-52; FL-001
A3: EP-02 | B3: PMCM Command and Coordination | C3: 5 | D3: C1, C2 | E3: FL-003, FL-008, FL-017; FR-88, FR-89, FR-90, FR-91
A4: EP-03 | B4: Briefing and Proposal | C4: 2 | D4: C2 | E4: FR-19, FR-58, FR-59, FR-60, FR-61, FR-62; FL-005, FL-006
A5: EP-04 | B5: Contract and Conforme | C5: 2 | D5: C2, C3 | E5: FR-03, FR-67, FR-68, FR-69, FR-70, FR-96, FR-97, New-SY4; FL-002
A6: EP-05 | B6: Floor Plan and Venue | C6: 4 | D6: C2 | E6: FR-08, FR-28, FR-29, FR-66, FR-80, FR-81, FR-82, FR-83, FR-84; FL-011, FL-016, FL-018
A7: EP-06 | B7: Compliance and Change Enablement | C7: 3 | D7: C3 | E7: FR-06, FR-07, New-SY3, New-SY4; FL-009
A8: EP-07 | B8: Supplier Network and Readiness | C8: 10 | D8: C1, C2, C3, C4 | E8: FR-14 to FR-18, FR-35 to FR-38, FR-49, FR-63, FR-64, FR-75 to FR-79, FR-87, FR-AI-06, New-S1 to New-S5, New-SUP1 to New-SUP4; FL-007, FL-022
A9: EP-08 | B9: Finance and Billing | C9: 3 | D9: C2, C3 | E9: FR-20, FR-21, FR-69, FR-92, FR-93, FR-94, New-P5; FL-010
A10: EP-09 | B10: File and Document Management | C10: 2 | D10: C2, C3 | E10: FR-04, FR-32, FR-33, FR-38, New-SEC3; FL-006, FL-024
A11: EP-10 | B11: Client Portal | C11: 3 | D11: C2, C3 | E11: FR-26 to FR-34, FR-65, FR-66, New-CL1, New-CL2; FL-004, FL-020
A12: EP-11 | B12: Coordinator Experience and Live Ops | C12: 5 | D12: C2, C3 | E12: FR-88 to FR-91, New-C1 to New-C4, New-CO1 to New-CO6; FL-008
A13: EP-12 | B13: Event Day Operations | C13: 6 | D13: C3, C4 | E13: FR-05, FR-40, FR-78, FR-AI-04, FR-AI-07, New-SY1, New-SY2; FL-019
... A19: EP-18 | B19: Design System and Shared UI | C19: 2 | D19: C1, C2 | E19: FL-016; packages/ui, design tokens, shared shell patterns

Sheet Tracker
A1: Epic ID | B1: Epic | C1: Story ID | D1: User Story | E1: Acceptance Criteria | F1: Priority (MoSCoW) | G1: Owner / Role | H1: Status | I1: Dependencies | J1: Notes | K1: Completion %
A2: EP-01 -- Inquiry and Client Onboarding
A3: EP-01 | B3: Inquiry and Client Onboarding | C3: EP-01-S01 | D3: As a prospective Client, I want to submit an event inquiry, so that PMCM can assess my event needs. | E3: 1. PASS: Public inquiry form is accessible without login or account creation. 2. PASS: Form captures all required fields: full name, contact number, email address, company or organization name, event type, preferred event date, expected headcount, and client type (individual or corporate). 3. PASS: Referral source dropdown is present with five confirmed values: Facebook, Website, BNI, Walk-In, Log on Behalf. Sixth value pending PA-62 resolution with Ms. Mys. 4. PASS: On submission, system checks for duplicate inquiry from same email or contact number; if duplicate detected, clear message shown and duplicate record not created. 5. PASS: If submitting email or contact number matches a previously rejected inquiry, previous rejection flag is surfaced to PMCM Admin on inquiry detail view (not shown to prospective client). 6. PASS: Submitted inquiry appears in PMCM Admin inquiry inbox with all submitted field values intact and readable. 7. PASS: Inquiry record stores client type field value (individual or corporate) and value is visible to PMCM Admin on detail view. 8. PASS: Submitter receives a confirmation acknowledgment (on-screen or email) after successful submission. 9. FAIL trigger: Form is inaccessible without login, any required field is absent, duplicate detection fails, previous rejection flag not surfaced to PMCM Admin, client type field missing, or confirmation acknowledgment absent. | F3: Must | G3: C (Ethan) | H3: Done | I3: None | J3: FR-01, FR-46, FR-51. PA-62 OPEN -- sixth referral source value pending Ms. Mys confirmation. Five confirmed values from codebase: Facebook, Website, BNI, Walk-In, Log on Behalf. | K3: =IF(H3="Done",1,IF(H3="In Progress",0.5,IF(H3="In Review",0.75,0))) -> 1
A4: EP-01 | B4: Inquiry and Client Onboarding | C4: EP-01-S02 | D4: As a PMCM Admin, I want to log an inquiry on behalf of a walk-in or phone client, so that all inquiries enter the same system regardless of channel. | E4: 1. PASS: PMCM Admin can access a Log Inquiry on Behalf function from within the PMCM command surface without navigating to the public inquiry form. 2. PASS: On-behalf form captures same required fields as public inquiry form: full name, contact number, email address, company or organization name, event type, preferred event date, expected headcount, client type, and referral source. 3. PASS: Resulting inquiry record is marked as logged on behalf of a client (channel: walk-in or phone), distinguishable from self-submitted inquiries in PMCM Admin inbox. 4. PASS: Non-PMCM actors (client, supplier, coordinator, guest) cannot access or trigger the logInquiryOnBehalf function. Any attempt returns an authorization denial with no data exposed. 5. PASS: Duplicate detection and previous rejection flag logic applies identically to on-behalf submissions as to public submissions. 6. PASS: Logged inquiry appears in PMCM Admin inquiry inbox with all field values intact, channel marker visible, and logging admin identity recorded. 7. FAIL trigger: On-behalf function is accessible to non-PMCM actors, channel marker is absent, duplicate detection is bypassed, or logging admin identity is not recorded. | F4: Must | G4: B (Francis) | H4: Done | I4: None | J4: FR-52; logInquiryOnBehalf; non-PMCM actors blocked; confirmed Live per File 9. | K4: =IF(H4="Done",1,IF(H4="In Progress",0.5,IF(H4="In Review",0.75,0))) -> 1
A5: EP-01 | B5: Inquiry and Client Onboarding | C5: EP-01-S03 | D5: As a PMCM Admin, I want to onboard a new client account after inquiry approval, so that the client can access their portal. | E5: 1. PASS: PMCM Admin can trigger client onboarding only after an inquiry has been approved; onboarding action unavailable on inquiries in any other status (Pending, Declined, Duplicate). 2. PASS: Onboarding creates a client account with login credentials and associates it with the approved inquiry record. 3. PASS: Newly created client account activates access to client portal (apps/client, port 3001) for that client and no other portal. 4. PASS: Client receives login credentials or an account activation link after onboarding is triggered by PMCM Admin. 5. PASS: Non-PMCM actors cannot trigger client onboarding. Any attempt returns an authorization denial with no data exposed. 6. PASS: Onboarding event produces an audit log entry recording the onboarding admin identity, timestamp, and associated inquiry ID. 7. FAIL trigger: Onboarding is triggerable before inquiry approval, client account is not associated with the inquiry record, client receives access to portals other than apps/client, or audit log entry is absent. | F5: Must | G5: D (Anthony) | H5: Done | I5: None | J5: FR-46; ClientOnboardingWorkflowService inside inquiry-onboarding module; confirmed Live per File 9. | K5: =IF(H5="Done",1,IF(H5="In Progress",0.5,IF(H5="In Review",0.75,0))) -> 1
A6: EP-01 | B6: Inquiry and Client Onboarding | C6: EP-01-S04 | D6: As a PMCM Admin, I want the referral source dropdown to capture exactly six confirmed values, so that inquiry source data is consistent and reportable. | E6: 1. PASS: Referral source dropdown is present on both the public inquiry form and the Log Inquiry on Behalf form. 2. PASS: Dropdown contains exactly six options. [PLACEHOLDER: five confirmed from codebase -- Facebook, Website, BNI, Walk-In, Log on Behalf. Sixth value pending PA-62 resolution with Ms. Mys.] 3. PASS: Referral source field is required; form cannot be submitted without a selection. 4. PASS: Selected referral source value is saved to the inquiry record and visible to PMCM Admin on inquiry detail view. 5. PASS: Referral source field value is preserved through duplicate detection and on-behalf submission flows without being lost or overwritten. 6. FAIL trigger: Dropdown is absent from either form, fewer or more than six options are present, field is optional and submittable without a selection, or saved value does not appear on PMCM Admin inquiry detail view. | F6: Must | G6: B (Francis) | H6: Done | I6: None | J6: FR-48; PA-62 OPEN -- Francis confirmed five values from codebase. Sixth value must be confirmed with Ms. Mys before AC item 2 is finalized. | K6: =IF(H6="Done",1,IF(H6="In Progress",0.5,IF(H6="In Review",0.75,0))) -> 1
A7: EP-02 -- PMCM Command and Coordination
A8: EP-02 | B8: PMCM Command and Coordination | C8: EP-02-S01 | D8: As a PMCM Admin, I want a command inbox showing critical alerts and pending actions, so that I can manage all active events from one surface. | E8: 1. PASS: Command inbox is accessible from the PMCM Admin dashboard in apps/event (port 3004) without additional navigation steps. 2. PASS: Inbox displays rows sourced from the PrismPmcmCommandInbox contract; each row contains at minimum: event name, alert type, severity level, and timestamp. 3. PASS: Critical severity alerts are visually distinguished from lower severity alerts (rose/red AlertTriangle icon confirmed per FL-017 build). 4. PASS: Inbox reflects current state of all active events; stale or resolved alerts do not persist after resolution. 5. PASS: Non-PMCM actors (client, supplier, coordinator, guest) cannot access the command inbox. Any attempt returns an authorization denial with no data exposed. 6. PASS: Inbox renders correctly in an empty state (no active alerts) with a clear empty state message; does not show a false all-clear when data fetch has not yet resolved. 7. PASS: Command inbox component is wired into EventDashboardClient.tsx at sections B, J, K, L as implemented; barrel export is present and resolves without error. 8. FAIL trigger: Inbox is inaccessible from PMCM dashboard, rows do not source from PrismPmcmCommandInbox contract, critical severity alerts are not visually distinguished, non-PMCM actors can access inbox data, or component throws an error on mount. | F8: Must | G8: B (Francis) | H8: Done | I8: None | J8: FL-017; PrismPmcmCommandInbox contract exists and feeds dashboard rows; confirmed Live per File 9. AC item 6 covers empty state only; error state is EP-02-S02 scope. | K8: =IF(H8="Done",1,IF(H8="In Progress",0.5,IF(H8="In Review",0.75,0))) -> 1
A9: EP-02 | B9: PMCM Command and Coordination | C9: EP-02-S02 | D9: As a PMCM Admin, I want the command inbox error state to correctly reflect system failures rather than showing a false all-clear, so that I am never misled about system health. | E9: 1. PASS: When command inbox data fetch fails (network error, API error, or timeout), inbox displays a visible error state with a clear message indicating a system failure; it does not display an empty inbox or an all-clear message. 2. PASS: Error state is visually distinct from both the empty state (no alerts) and the loaded state (alerts present); a user cannot mistake a fetch failure for a genuine all-clear. 3. PASS: Error state does not expose raw error details, stack traces, or internal system information to the PMCM Admin. 4. PASS: When underlying data fetch recovers, inbox transitions from error state to the correct loaded or empty state without requiring a full page reload. 5. PASS: The false all-clear chain identified in FL-017 post-build deferred item 1 is fully resolved; no code path exists where a fetch failure renders the inbox as empty-and-healthy. 6. FAIL trigger: A fetch failure renders the inbox as empty or all-clear, error state is visually indistinguishable from empty state, raw error details are exposed to the user, or recovery from error state requires a full page reload. | F9: Must | G9: B (Francis) | H9: Done | I9: EP-02-S01 | J9: FL-017 deferred item 1 RESOLVED. Commit e0f99c0. Amber AlertTriangle error panel and '!' badge implemented. SILENT-001 and SILENT-008 cleared. Verified in Docker. | K9: =IF(H9="Done",1,IF(H9="In Progress",0.5,IF(H9="In Review",0.75,0))) -> 1
A10: EP-02 | B10: PMCM Command and Coordination | C10: EP-02-S03 | D10: As a PMCM Admin, I want to click through command inbox items to the relevant event workspace, so that I can act on alerts without manual navigation. | E10: 1. PASS: Each command inbox item is clickable and navigates the PMCM Admin directly to the relevant event workspace without additional navigation steps. 2. PASS: Destination route is correct for each alert type; a supplier alert routes to the supplier section, a billing alert routes to the billing section, and so on. 3. PASS: Click-through navigation preserves the inbox state; returning to the inbox after navigating away does not reset or reload the inbox unexpectedly. 4. PASS: Clicking a resolved or stale inbox item either routes correctly or shows a clear message that the item is no longer active; it does not route to a broken or empty workspace state. 5. PASS: Non-PMCM actors cannot trigger or access any click-through navigation route from the command inbox. 6. FAIL trigger: Any inbox item is non-clickable, click routes to an incorrect workspace section, click-through exposes non-PMCM workspace data to unauthorized actors, or a stale item click results in a broken route with no user feedback. | F10: Should | G10: B (Francis) | H10: Done | I10: EP-02-S01 | J10: FL-017 deferred item 2 RESOLVED. Commit a97498f. InboxItem conditionally wraps in Link using item.href. Verified in Docker. 404 on destination is expected and out of FL-017 scope. | K10: =IF(H10="Done",1,IF(H10="In Progress",0.5,IF(H10="In Review",0.75,0))) -> 1
A11: EP-02 | B11: PMCM Command and Coordination | C11: EP-02-S04 | D11: As a PMCM Admin, I want the command inbox mounted in its final approved location, so that the layout matches the accepted T03 design. | E11: 1. PASS: Command inbox is mounted at the location specified in the T03 acceptance notes, not in a standalone stub location. 2. PASS: Mounting location is confirmed by at least one other owner as matching the T03 design before this story moves to Done. 3. PASS: Mounted location does not introduce layout regressions on any other section of the PMCM Admin dashboard. 4. PASS: Command inbox retains all behavior from EP-02-S01, EP-02-S02, and EP-02-S03 after relocation; no AC items from those stories regress as a result of the mount change. 5. FAIL trigger: Inbox remains in standalone stub location after branches merge, mounting introduces layout regressions, or any prior AC item from EP-02-S01 through EP-02-S03 regresses after relocation. | F11: Could | G11: B (Francis) | H11: Done | I11: EP-02-S01, EP-02-S02, EP-02-S03 | J11: FL-017 deferred item 3 RESOLVED as non-issue. Mounting location requirement came from t03-acceptance-notes.md -- a Claude Code-generated memory file never approved by team, adviser, or client. Not in ClickUp. Not in whole-system calendar. Standalone route is correct per team plan. No code change needed. t03-acceptance-notes.md must be deleted from Claude Code memory. | K11: =IF(H11="Done",1,IF(H11="In Progress",0.5,IF(H11="In Review",0.75,0))) -> 1
A12: EP-02 | B12: PMCM Command and Coordination | C12: EP-02-S05 | D12: As a PMCM Admin, I want to view the full coordinator directory and issue assignment commands from the command surface, so that I can assign the right coordinators to each event without leaving the PMCM app. | E12: 1. PASS: PMCM Admin can view the full coordinator directory from within apps/event (port 3004) without navigating away from the command surface. 2. PASS: Directory displays each coordinator name, assigned role tags, skills tags, and current availability status. 3. PASS: PMCM Admin can issue an assignment command selecting a coordinator for a specific event and role; assignment is recorded in staffing-ops module. 4. PASS: System detects double-booking: if a coordinator is already assigned to another event on the same date, a clear warning is shown before the assignment is confirmed (FR-88). Assignment is not blocked automatically but warning must be visible and dismissible only with explicit PMCM Admin confirmation. 5. PASS: PMCM Admin can initiate a coordinator withdrawal or replacement from the same surface (FR-89); the replacement command updates the assignment record and logs the change. 6. PASS: After assignment is issued, coordinator assignment status appears as Pending Acknowledgment on the PMCM dashboard until the coordinator confirms (EP-11-S01 response side); PMCM Admin can see which assignments are unacknowledged. 7. PASS: FR-90 PMCM tracking side: PMCM Admin can track acknowledgment status per coordinator per event from this surface. 8. PASS: Coordinator directory and assignment data are accessible to PMCM Admin only; coordinator, client, supplier, and guest actors cannot access directory payloads or assignment command routes. 9. PASS: same_tx pattern is used for coordinator assignment commands per access-control module specification; assignment and audit log entry are atomic. 10. FAIL trigger: Double-booking warning is absent or suppressible without explicit confirmation, assignment data is accessible to non-PMCM actors, Pending Acknowledgment status is not shown after assignment is issued, or assignment and audit entry are not written atomically. | F12: Must | G12: B (Francis) | H12: In Progress | I12: None | J12: Absorbs EP-11-S04 (deleted from original scope). FL-008; staffing-ops module. FR-90 PMCM tracking side here; EP-11-S01 covers coordinator acknowledgment response side. ACTION: Francis to start after EP-04-S01. | K12: =IF(H12="Done",1,IF(H12="In Progress",0.5,IF(H12="In Review",0.75,0))) -> 0.5
A13: EP-03 -- Briefing and Proposal
A14: EP-03 | B14: Briefing and Proposal | C14: EP-03-S01 | D14: As a PMCM Admin, I want to create and send an event briefing to the client, so that expectations are aligned before proposal generation. | E14: 1. PASS: PMCM Admin can create an event briefing from within apps/event after conforme is signed (EP-04-S01 gate); briefing creation unavailable before conforme. 2. PASS: Briefing form captures at minimum: event objectives, scope of services, timeline and key milestones, PMCM responsibilities, and client responsibilities. 3. PASS: PMCM Admin can send the briefing to the client; client receives access to the briefing inside the client portal (apps/client). 4. PASS: Client can complete their portion of the briefing form inside the client portal; PMCM Admin is notified when client submission is received. 5. PASS: Briefing record is stored and retrievable per event; visible to PMCM Admin and the assigned client only. 6. PASS: Briefing status is trackable (Sent, Client Responded, Complete); status is visible on the PMCM command surface. 7. PASS: EP-03-S02 (proposal generation) is gated on briefing completion; the proposal action is unavailable until briefing status is Complete. 8. PASS: Supplier, coordinator, and guest actors cannot access briefing records or briefing form data. 9. FAIL trigger: Briefing is createable before conforme is signed, client cannot access the briefing in their portal, proposal action is available before briefing is complete, or briefing data is accessible to non-PMCM non-client actors. | F14: Must | G14: B (Francis) | H14: To Do | I14: EP-04-S01 | J14: FR-58; PA-81 phase ownership provisionally confirmed C2. EventBriefingPanel confirmed present in apps/event. GATE: EP-04-S01 must be Done first. | K14: =IF(H14="Done",1,IF(H14="In Progress",0.5,IF(H14="In Review",0.75,0))) -> 0
A15: EP-03 | B15: Briefing and Proposal | C15: EP-03-S02 | D15: As a PMCM Admin, I want to generate and send a proposal to the client, so that the client can review and respond before conforme. | E15: 1. PASS: PMCM Admin can generate a proposal from within apps/event after the event briefing is complete (EP-03-S01 gate); proposal action unavailable before briefing is Complete. 2. PASS: Proposal is handled by CommercialWorkflowService inside commercial-ops. 3. PASS: Proposal contains at minimum: Executive Summary, Event Concept, Service Package Summary, Investment Summary, and Payment Schedule. 4. PASS: PMCM Admin reviews and finalizes the proposal before sending; proposal cannot be sent in draft state without explicit PMCM Admin send action. 5. PASS: Client receives the proposal inside the client portal and can view all five sections. 6. PASS: Client can respond to the proposal (accept or request revision); PMCM Admin is notified of the client response. 7. PASS: Proposal revision history is stored; PMCM Admin can view prior proposal versions per event. 8. PASS: Proposal data (investment summary, payment schedule) is not visible to supplier, coordinator, or guest actors. 9. PASS: Conforme upload (EP-04-S01) is available only after the client has accepted the proposal; conforme action is gated on proposal acceptance. 10. FAIL trigger: Proposal is sendable before briefing is complete, proposal is sent without explicit PMCM Admin send action, financial data is accessible to non-PMCM non-client actors, or conforme action is available before proposal is accepted. | F15: Must | G15: B (Francis) | H15: To Do | I15: EP-03-S01 | J15: FR-60; commercial-ops; CommercialWorkflowService. AI proposal drafting (FR-AI-03) is Phase 2 scope and a separate story (EP-16-S02); this story covers manual proposal workflow only. | K15: =IF(H15="Done",1,IF(H15="In Progress",0.5,IF(H15="In Review",0.75,0))) -> 0
A16: EP-04 -- Contract and Conforme
A17: EP-04 | B17: Contract and Conforme | C17: EP-04-S01 | D17: As a PMCM Admin, I want to upload a signed conforme document, so that the client portal, billing workspace, and event workspace are atomically activated. | E17: 1. PASS: PMCM Admin can upload a signed conforme document from within apps/event; upload is handled via the inquiry-onboarding module uploadConforme path. 2. PASS: Conforme upload accepts PDF format only; non-PDF uploads are rejected with a clear error message. 3. PASS: On successful conforme upload, the following are activated atomically in a single transaction: client portal access for the assigned client, billing workspace for the event, and event workspace for PMCM Admin. 4. PASS: If any part of the atomic activation fails, none of the three activations complete; the system rolls back and PMCM Admin sees a clear failure message with no partial activation state. 5. PASS: Conforme document is stored and retrievable per event; PMCM Admin can view the uploaded conforme on the event record. 6. PASS: The 50% downpayment milestone is created as a billing record downstream (EP-08-S01 consequence); this story AC does not cover billing generation logic directly pending PA-109 resolution. 7. PASS: Client portal, billing workspace, and event workspace are inaccessible to their respective actors before conforme is uploaded; no partial access is granted on proposal acceptance alone. 8. PASS: Conforme document is not accessible to supplier, coordinator, or guest actors. 9. PASS: Conforme upload event produces an audit log entry recording the uploading admin identity, timestamp, and event ID. 10. FAIL trigger: Non-PDF file is accepted, atomic activation is partial, rollback does not occur on failure, conforme document is accessible to non-PMCM non-client actors, or audit log entry is absent on upload. | F17: Must | G17: B (Francis) | H17: In Progress | I17: None | J17: FR-03; conforme = master gate. PA-109 OPEN -- Anthony must confirm whether uploadConforme calls billing logic directly or routes through FinanceOpsModule. HIGHEST PRIORITY C2 DELIVERY -- gates 19 downstream stories. ACTION: Francis to start immediately. ACTION: Raise PA-109 with Anthony. | K17: =IF(H17="Done",1,IF(H17="In Progress",0.5,IF(H17="In Review",0.75,0))) -> 0.5
A18: EP-04 | B18: Contract and Conforme | C18: EP-04-S02 | D18: As a PMCM Admin, I want to generate and manage a contract or MOA for large clients, so that the legal agreement is documented and notarized where required. | E18: 1. PASS: PMCM Admin can generate a contract or MOA from within apps/event after conforme is signed (EP-04-S01 gate). 2. PASS: Contract or MOA captures at minimum: party names, event scope, payment terms, cancellation and postponement clauses, and notarization requirement flag. 3. PASS: Dual signing path is supported: e-signature is the primary path; physical signature fallback is available and documented per event. 4. PASS: PMCM Admin can track contract status (Draft, Sent, Signed, Notarized) per event. 5. PASS: Signed contract or MOA is stored and retrievable per event; PMCM Admin can view and download it. 6. PASS: Contract or MOA is not accessible to supplier, coordinator, or guest actors. 7. FAIL trigger: Contract is generatable before conforme is signed, dual signing path is not supported, signed document is not stored per event, or non-PMCM non-client actors can access contract data. | F18: Should | G18: B (Francis) | H18: To Do | I18: EP-04-S01 | J18: FR-67, FR-68; MOA for large clients; notarization requirement noted; dual signing path (e-signature primary, physical fallback). | K18: =IF(H18="Done",1,IF(H18="In Progress",0.5,IF(H18="In Review",0.75,0))) -> 0
A19: EP-05 -- Floor Plan and Venue
A20: EP-05 | B20: Floor Plan and Venue | C20: EP-05-S01 | D20: As a PMCM Admin, I want to build and publish an official floor plan for an event, so that the approved layout is available to all relevant parties. | E20: 1. PASS: PMCM Admin can create an official floor plan from within apps/event after conforme is signed (EP-04-S01 gate); floor plan creation is unavailable before conforme. 2. PASS: Floor plan creation is handled by FloorPlanWorkflowService inside the floorplan module. 3. PASS: PMCM Admin can publish the official floor plan; published snapshot is stored and retrievable per event. 4. PASS: Only PMCM Admin and system actors can mutate the official floor plan state; client, supplier, coordinator, and guest actors cannot mutate official floor plan state. 5. PASS: Client, supplier, and coordinator actors can fetch the published approved snapshot per their role permissions; no actor can access a snapshot beyond their confirmed role boundary. 6. PASS: Ocular visit task (EP-10-S03) must be marked complete by PMCM Admin before floor plan creation is available, unless PMCM Admin override path is confirmed (PA-59 resolution required). 7. PASS: FLOORPLAN_COMMANDS port is used for all write operations; no direct Prisma calls bypass the port abstraction. 8. FAIL trigger: Floor plan is createable before conforme is signed, non-PMCM actors can mutate official floor plan state, FLOORPLAN_COMMANDS port is bypassed, or ocular visit gate is absent without confirmed override path. | F20: Must | G20: B (Francis) | H20: To Do | I20: EP-04-S01 | J20: FL-016; FR-80; floorplan module confirmed extracted; FloorPlanWorkflowService; PMCM/system actors mutate official floorplans only; canvas/editor persistence unchanged. PA-59 OPEN on ocular visit override path. | K20: =IF(H20="Done",1,IF(H20="In Progress",0.5,IF(H20="In Review",0.75,0))) -> 0
A21: EP-05 | B21: Floor Plan and Venue | C21: EP-05-S02 | D21: As a Client, I want to submit my venue and layout preferences, so that PMCM can incorporate them into the official floor plan. | E21: 1. PASS: Client can submit venue and layout preferences from within the client portal (apps/client) after conforme is signed (EP-04-S01 gate). 2. PASS: Preference submission is clearly labeled as a preference draft, not an official floor plan; client cannot mistake their preference submission for the official layout. 3. PASS: Client preferences are stored and retrievable by PMCM Admin per event; PMCM Admin decides whether to incorporate preferences into the official floor plan. 4. PASS: Client can submit preferences only once; revision requires PMCM Admin to reopen the preference window. 5. PASS: Client cannot view or access the official floor plan state until PMCM Admin publishes it. 6. PASS: Supplier, coordinator, and guest actors cannot access client preference submissions. 7. FAIL trigger: Client preference submission is labeled as an official floor plan, client can mutate official floor plan state, or non-client non-PMCM actors can access preference data. | F21: Must | G21: C (Ethan) | H21: To Do | I21: EP-04-S01, EP-05-S01 | J21: FL-018; FR-28; client submits preferences only -- cannot mutate official state. Labeled as preference draft not a floor plan. | K21: =IF(H21="Done",1,IF(H21="In Progress",0.5,IF(H21="In Review",0.75,0))) -> 0
A22: EP-05 | B22: Floor Plan and Venue | C22: EP-05-S03 | D22: As a Client, I want to view the approved floor plan and submit revision comments, so that I can confirm the layout before the event. | E22: 1. PASS: Client can view the approved floor plan snapshot from within the client portal after PMCM Admin publishes it (EP-05-S01 gate). 2. PASS: Client view is read-only; client cannot edit or mutate the official floor plan in any way. 3. PASS: Client can submit revision comments on the published floor plan; comments are routed to PMCM Admin for review. 4. PASS: Only the designated primary client contact can submit revision comments; non-primary contacts have read-only access. 5. PASS: Floor plan is locked once approved by PMCM Admin; no further client revision comments are accepted after approval. 6. PASS: Supplier, coordinator, and guest actors cannot access the client floor plan view or revision comments. 7. FAIL trigger: Client can mutate official floor plan state, non-primary client contacts can submit revision comments, floor plan remains open for revision after PMCM Admin approval, or non-authorized actors can access floor plan data. | F22: Must | G22: C (Ethan) | H22: To Do | I22: EP-05-S01 | J22: FR-29, FR-83; read-only official snapshot access; client annotations actionable only for designated primary contact; floor plan locked once approved. | K22: =IF(H22="Done",1,IF(H22="In Progress",0.5,IF(H22="In Review",0.75,0))) -> 0
A23: EP-05 | B23: Floor Plan and Venue | C23: EP-05-S04 | D23: As a PMCM Admin, I want a floor plan canvas editor with a draggable element library, so that I can draw and adjust venue layouts using interactive tools. | E23: 1. 1. PASS: Floor plan canvas editor is accessible to PMCM Admin from within apps/event; editor uses a custom native HTML5 Canvas renderer for canvas interaction (confirmed implementation choice; supersedes original Konva.js/Fabric.js planning note). 2. PASS: Pre-built draggable elements library is available by category (e.g., tables, chairs, stage, podium, AV equipment); elements are draggable onto the canvas. 3. PASS: Canvas editor persistence shape is unchanged from pre-extraction behavior; no regression is introduced to existing canvas save and load behavior. 4. PASS: PMCM Admin can save, reload, and update the canvas state; saved state is retrievable per event. 5. PASS: Editor is accessible only to PMCM Admin; client, supplier, coordinator, and guest actors cannot access the canvas editor. 6. N/A, out of scope: "Venue Styling" and decor/moodboard workflows (FR-09, FR-15, FR-43) exist only in Phase 2 planning documentation with zero implementation in this codebase. This AC describes SB-14 (Venue Styling Hard Dependency Lock), a Change Enablement Engine sub-ticket concern that belongs to a future epic, not the floor plan canvas editor. No action required here until that epic is built. 7. FAIL trigger: Canvas editor is accessible to non-PMCM actors, pre-built elements library is absent, canvas persistence behavior regresses from pre-extraction state, or styling sub-tickets proceed before floor plan approval. | F23: Must | G23: B (Francis) | H23: In Review | I23: None | J23: FR-80; Konva.js or Fabric.js; pre-built draggable elements by category; canvas/editor persistence shape unchanged. Sub-ticket hard dependency confirmed -- styling blocked until floor plan approved. | K23: =IF(H23="Done",1,IF(H23="In Progress",0.5,IF(H23="In Review",0.75,0))) -> 0.75
A24: EP-06 -- Compliance and Change Enablement
A25: EP-06 | B25: Compliance and Change Enablement | C25: EP-06-S01 | D25: As a PMCM Admin, I want the system to validate event requirements against compliance rules, so that no required item is missed before the event. | E25: 1. PASS: Compliance validation is accessible to PMCM Admin from within apps/event after conforme is signed (EP-04-S01 gate). 2. PASS: Compliance Engine performs rule-based field-presence validation: it checks whether required fields and documents are present per defined compliance rules, not semantic analysis of content. NLP = benchmark only (89.1% precision, Abualhaija et al. 2023); this must not be overstated in any AC or documentation. 3. PASS: Compliance rules are managed by ComplianceWorkflowService inside compliance-ops via COMPLIANCE_COMMANDS port; rules are stored per event type or per event. 4. PASS: Validation results are returned via COMPLIANCE_READER port; results distinguish between Must-Fix Items (blocking) and Advisory Items (non-blocking). 5. PASS: PMCM Admin can view the full compliance validation result per event, including which specific rules passed and which failed. 6. PASS: AI advisory layer (FR-10+) is explicitly not part of this story; no AI-generated compliance suggestions are present here. AI advisory is Phase 2 scope gated on EP-15-S05. 7. PASS: Supplier, coordinator, client, and guest actors cannot access compliance rule definitions or validation results. 8. PASS: Compliance validation result feeds the defense and readiness gate (EP-06-S02); EP-06-S02 cannot be attempted until at minimum one compliance validation run has been recorded. 9. FAIL trigger: Compliance Engine performs semantic NLP analysis rather than field-presence validation, AI advisory layer is present in this story scope, validation results are accessible to non-PMCM actors, or COMPLIANCE_READER and COMPLIANCE_COMMANDS ports are bypassed by direct Prisma calls. | F25: Must | G25: B (Francis) | H25: To Do | I25: EP-04-S01 | J25: FR-06; compliance-ops; ComplianceWorkflowService; three-layer architecture. NLP = benchmark only -- critical rule. AI advisory (FR-10+) is Phase 2 scope only. | K25: =IF(H25="Done",1,IF(H25="In Progress",0.5,IF(H25="In Review",0.75,0))) -> 0
A26: EP-06 | B26: Compliance and Change Enablement | C26: EP-06-S02 | D26: As a PMCM Admin, I want a defense and readiness gate check, so that I can confirm all pre-event conditions are met before approving event execution. | E26: 1. PASS: Defense and readiness gate check is accessible to PMCM Admin from within apps/event; not accessible to client, supplier, coordinator, or guest actors. 2. PASS: Gate check is handled by defenseReadiness composition inside compliance-ops; it aggregates compliance validation results, supplier confirmation status, payment milestone status, and floor plan approval status into a single readiness report. 3. PASS: Pre-Event Readiness Report is generated and displays: overall readiness status (Ready or Not Ready), a list of all Must-Fix Items blocking readiness, and a list of all Advisory Items not blocking readiness. 4. PASS: Event is flagged as Not Ready until all Must-Fix Items are resolved; PMCM Admin cannot mark an event as approved for execution while Must-Fix Items remain. 5. PASS: Each resolved Must-Fix Item is recorded with timestamp and resolving admin identity in the audit trail. 6. PASS: Pre-Event Readiness Report is retrievable per event; historical readiness runs are stored, not overwritten. 7. PASS: Client, supplier, coordinator, and guest actors cannot access the Pre-Event Readiness Report or defenseReadiness composition results. 8. FAIL trigger: Event can be approved for execution with open Must-Fix Items, defenseReadiness composition is accessible to non-PMCM actors, readiness report is overwritten rather than stored per run, or Must-Fix Item resolution is not recorded in audit trail. | F26: Must | G26: B (Francis) | H26: To Do | I26: EP-06-S01 | J26: FL-015; compliance-ops; defenseReadiness composition; client/guest denied. Pre-Event Readiness Report generated. | K26: =IF(H26="Done",1,IF(H26="In Progress",0.5,IF(H26="In Review",0.75,0))) -> 0
A27: EP-06 | B27: Compliance and Change Enablement | C27: EP-06-S03 | D27: As a PMCM Admin, I want to raise and classify change requests and enforce the change freeze window, so that all changes are audited and no unauthorized scope changes occur within 5 days of the event. | E27: 1. PASS: PMCM Admin can raise a change request from within apps/event after conforme is signed; change request captures: change type, description, requester, classification (Standard, Emergency, or Operational Adjustment), and affected event. 2. PASS: Change freeze is automatically enforced at exactly 5 days before the event date; client scope changes are locked after the freeze window opens. 3. PASS: Internal operational adjustments by PMCM Admin are always permitted regardless of freeze window status. 4. PASS: Emergency Change classification is available during the freeze window for PMCM Admin; Emergency Changes require explicit classification and produce an audit log entry. 5. PASS: Supplier withdrawal within the freeze window automatically triggers Emergency Change classification and activates the PARE flow (EP-12-S02 dependency). 6. PASS: All change requests are recorded in the audit trail with timestamp, classifying admin identity, and classification rationale. 7. PASS: Change request history is retrievable per event by PMCM Admin; client can view their own submitted change requests but cannot view PMCM internal change request records. 8. PASS: Supplier, coordinator, and guest actors cannot raise or view change requests. 9. FAIL trigger: Change freeze is not enforced at exactly 5 days before event, client scope changes are accepted after freeze window opens, Emergency Change is available to non-PMCM actors, or change requests are not recorded in audit trail. | F27: Must | G27: B (Francis) | H27: To Do | I27: EP-04-S01 | J27: New-SY3; CE rule engine and freeze enforcement only. Change freeze = 5 days before event. EP-12-S02 (PARE) and EP-12-S03 (supplier withdrawal) both depend on this story. | K27: =IF(H27="Done",1,IF(H27="In Progress",0.5,IF(H27="In Review",0.75,0))) -> 0
A28: EP-07 -- Supplier Network and Readiness
A29: EP-07 | B29: Supplier Network and Readiness | C29: EP-07-S01 | D29: As a PMCM Admin, I want to manage a supplier directory with category tagging, reliability notes, and certifications, so that I can select the best supplier per category. | E29: 1. PASS: Supplier directory is accessible to PMCM Admin from apps/event and displays all registered suppliers. 2. PASS: Each supplier record includes: supplier name, assigned category (one of 8 confirmed: Production, Technicals, Digital Registration, Documentation, Food and Beverages, Talents, Logistics, Program and Manpower), Tier designation (Tier 1 or Tier 2), BNI Member flag, and Pending First Event status for newly approved suppliers. 3. PASS: PMCM Admin can add reliability notes to a supplier record; notes are stored and retrievable on subsequent views. 4. PASS: PMCM Admin can attach certifications to a supplier record. 5. PASS: Aggregate review rating is visible on the supplier record to PMCM Admin only; not exposed to supplier, client, guest, or coordinator actors. 6. PASS: BNI Member flag is toggleable by PMCM Admin and persists on the record. 7. PASS: Supplier directory is filterable or searchable by at minimum category and tier designation. 8. PASS: Supplier, client, guest, and coordinator actors cannot access the supplier directory or any supplier record detail payload. 9. FAIL trigger: Any of the 8 supplier categories is absent, aggregate review rating is visible to non-PMCM actors, BNI flag does not persist, reliability notes are not stored, or non-PMCM actors can access directory data. | F29: Must | G29: B (Francis) | H29: Done | I29: None | J29: FR-14, FR-35; confirmed Live per File 9. BNI member flag; aggregate review rating PMCM-only; 8 confirmed categories. | K29: =IF(H29="Done",1,IF(H29="In Progress",0.5,IF(H29="In Review",0.75,0))) -> 1
A30: EP-07 | B30: Supplier Network and Readiness | C30: EP-07-S02 | D30: As a PMCM Admin, I want to send quote requests to Tier 1 and Tier 2 suppliers per category, so that I have competitive quotes before confirming suppliers. | E30: 1. PASS: PMCM Admin can send a quote request to Tier 1 and Tier 2 suppliers for any of the 8 supplier categories independently. 2. PASS: Quote request includes at minimum: event details, required service scope, and submission deadline. 3. PASS: Supplier receives notification of the quote request. 4. PASS: Supplier can submit one revision to their quote before the deadline; a second revision attempt after the first revision is blocked with a clear message. 5. PASS: Quote is locked and no further supplier edits are permitted after PMCM Admin selects the supplier. 6. PASS: PMCM Admin can view all received quotes for a category side by side before making a selection. 7. PASS: Quote request record is stored and retrievable in supplier-ops module; no quote data is exposed to client, guest, or coordinator actors. 8. FAIL trigger: Quote revision limit is not enforced, quote remains editable after supplier selection, quote data is accessible to non-PMCM or non-supplier actors, or quote request record is not persisted. | F30: Must | G30: B (Francis) | H30: Done | I30: EP-07-S01 | J30: FR-17; confirmed Live per File 9. One revision allowed before deadline. Quote locked after supplier selected. | K30: =IF(H30="Done",1,IF(H30="In Progress",0.5,IF(H30="In Review",0.75,0))) -> 1
A31: EP-07 | B31: Supplier Network and Readiness | C31: EP-07-S03 | D31: As a Supplier, I want to review and confirm my availability and quote, so that PMCM can formally assign me to the event. | E31: 1. PASS: Supplier can view the full quote request details sent by PMCM Admin inside the supplier portal (apps/supplier, port 3002). 2. PASS: Supplier must explicitly confirm availability and review and accept the quoted terms before formal assignment is recorded. 3. PASS: Supplier confirmation triggers a status update visible to PMCM Admin on the quote request record. 4. PASS: No raw AI output is shown to the supplier at any point in this flow; all supplier-facing communications are PMCM-reviewed before sending (FR-AI-04b). 5. PASS: Supplier can only view and act on their own quote requests; they cannot access quote requests sent to other suppliers for the same event or category. 6. PASS: Formal assignment is only recorded after supplier confirmation is received; PMCM Admin cannot mark a supplier as assigned without supplier confirmation on record. 7. PASS: Supplier actor cannot access client data, coordinator data, or PMCM internal cost or planning data at any point in this flow. 8. FAIL trigger: Supplier is formally assigned without their explicit confirmation, raw AI output is surfaced to the supplier, supplier can view another supplier quote request, or supplier can access non-supplier data payloads. | F31: Must | G31: C (Ethan) | H31: Done | I31: EP-07-S02 | J31: FR-37; confirmed Live per File 9. No raw AI output to suppliers -- critical role boundary. | K31: =IF(H31="Done",1,IF(H31="In Progress",0.5,IF(H31="In Review",0.75,0))) -> 1
A32: EP-07 | B32: Supplier Network and Readiness | C32: EP-07-S04 | D32: As a PMCM Admin, I want to send a pre-event readiness confirmation request to each supplier 7 days before the event, so that last-minute issues are caught before event day. | E32: 1. PASS: System triggers a readiness confirmation request to each confirmed supplier exactly 7 days before the event date without requiring manual PMCM Admin initiation. 2. PASS: Readiness confirmation request presents the supplier with a one-tap confirmation action. 3. PASS: Supplier confirms readiness with a one-tap yes/no action. If confirming with a concern, supplier can optionally add a free-text note visible to PMCM Admin only. FR-64 full communication thread is Phase 2 scope and is not part of this story. [PA-77 RESOLVED] 4. PASS: PMCM Admin receives a consolidated readiness status per event showing which suppliers have confirmed and which have not responded. 5. PASS: Suppliers who have not responded by 48 hours before the event are flagged with a clear alert on the PMCM command surface. 6. PASS: Readiness confirmation records are stored per supplier per event and feed the Pre-Event Readiness Report (EP-06-S02). 7. PASS: Supplier confirmation is visible only to PMCM Admin; client, coordinator, and guest actors cannot access supplier readiness records. 8. FAIL trigger: Readiness request is not triggered automatically at 7 days, unresponsive supplier is not flagged at 48 hours, readiness records are accessible to non-PMCM actors, or confirmation record does not feed EP-06-S02. | F32: Must | G32: B (Francis) | H32: To Do | I32: EP-07-S03 | J32: New-SUP2; FL-022; PA-77 RESOLVED -- concern flagging via optional free-text note (Prism scope); FR-64 full communication thread is Phase 2 scope only. | K32: =IF(H32="Done",1,IF(H32="In Progress",0.5,IF(H32="In Review",0.75,0))) -> 0
A33: EP-07 | B33: Supplier Network and Readiness | C33: EP-07-S05 | D33: As a Supplier, I want to update my on-site arrival and setup status during the event, so that PMCM can track supplier presence in real time. | E33: 1. PASS: Supplier can update their on-site status from within the supplier portal (apps/supplier) during the event using exactly three status buttons: Arrived, Set Up and Ready, Done and Leaving. 2. PASS: Supplier can attach an optional photo to each status update; photo upload is optional, not required, for the status to be recorded. 3. PASS: Each status update is recorded with timestamp and supplier identity; updates are visible to PMCM Admin in real time on the live operations dashboard (EP-12-S01). 4. PASS: Each status update carries one of two verification levels: Self-Reported (supplier own update) or Verified. [PLACEHOLDER: confirm which role performs Verified level and through which surface -- PA-76 OPEN. Ms. Mys must confirm.] 5. PASS: Supplier can only update their own event status; they cannot view or update status records for other suppliers assigned to the same event. 6. PASS: Client, coordinator, and guest actors cannot access or update supplier status records. 7. FAIL trigger: Status buttons are not exactly three, status updates are not visible in real time on PMCM live ops dashboard, supplier can update another supplier status, or non-supplier non-PMCM actors can access supplier status data. | F33: Must | G33: C (Ethan) | H33: Done | I33: EP-07-S03 | J33: New-SUP1; confirmed Live per File 9. PA-76 OPEN -- Ms. Mys must confirm who performs Verified level and through which surface. ACTION: Ask Ms. Mys. | K33: =IF(H33="Done",1,IF(H33="In Progress",0.5,IF(H33="In Review",0.75,0))) -> 1
A34: EP-07 | B34: Supplier Network and Readiness | C34: EP-07-S06 | D34: As a PMCM Admin or prospective Supplier, I want to register a new supplier on the platform, so that they can be added to the active supplier network. | E34: 1. PASS: A public-facing supplier registration form is accessible without login or account creation. 2. PASS: Registration form captures at minimum: supplier name, primary contact name, contact number, email address, service category (one of the 8 confirmed categories), and a brief description of services. 3. PASS: BNI Member toggle is available on the registration form and the selected value is stored on the supplier application record. 4. PASS: Submitted application is routed to the Supplier Applications inbox in PMCM Admin (EP-07-S09). 5. PASS: Applicant receives a confirmation acknowledgment on submission. 6. PASS: Submitted application is not automatically approved; PMCM Admin must take explicit action on each application (EP-07-S09). 7. PASS: Supplier, client, guest, and coordinator actors with existing accounts cannot submit a second registration through this form without PMCM Admin awareness. 8. FAIL trigger: Registration form requires login or account creation, BNI Member toggle is absent, submitted application is not routed to PMCM Admin inbox, or application is automatically approved without PMCM Admin action. | F34: Must | G34: C (Ethan) | H34: To Do | I34: None | J34: New-SUP3 = New-EX1 = New-S1; PA-74 OPEN -- canonical FR number and name TBD. One story only. Public-facing application form. Routes to EP-07-S09 (Supplier Applications inbox). | K34: =IF(H34="Done",1,IF(H34="In Progress",0.5,IF(H34="In Review",0.75,0))) -> 0
A35: EP-07 | B35: Supplier Network and Readiness | C35: EP-07-S07 | D35: As Ms. Mys or EA, I want to review each assigned supplier after an event is closed, so that performance ratings are recorded privately and inform future tier decisions. | E35: 1. PASS: Ms. Mys and EA can access the Internal Supplier Review surface after an event is closed; no other actor can access this surface. 2. PASS: Review form captures: overall star rating (1 to 5) and category-specific dimension ratings per supplier. 3. PASS: A private notes field is available per supplier review; notes are stored and visible only to Ms. Mys and EA. 4. PASS: Review ratings are not visible to the reviewed supplier, other suppliers, clients, coordinators, or guest actors under any circumstance. 5. PASS: PA-71 must be resolved before Done: Ms. Mys must confirm EA full role name and whether EA has own system login or is a sub-role under PMCM Admin. 6. PASS: Review ratings feed EP-07-S08 (tier decisions) and the Event Insights Card (EP-14-S01 New-P2). 7. FAIL trigger: Any actor other than Ms. Mys and EA can access the Internal Supplier Review surface, ratings are visible to the reviewed supplier, or PA-71 is unresolved at Done call. | F35: Must | G35: B (Francis) | H35: Done | I35: None | J35: New-S5; confirmed Live per File 9. PA-71 OPEN -- Ms. Mys must confirm EA full role name and login type. ACTION: Ask Ms. Mys. | K35: =IF(H35="Done",1,IF(H35="In Progress",0.5,IF(H35="In Review",0.75,0))) -> 1
A36: EP-07 | B36: Supplier Network and Readiness | C36: EP-07-S08 | D36: As a PMCM Admin, I want to assess supplier performance across multiple events and manually adjust their tier designation, so that the supplier network reflects real reliability history. | E36: 1. PASS: PMCM Admin can view accumulated post-event review ratings per supplier across multiple events from within apps/event. 2. PASS: PMCM Admin can manually upgrade or downgrade a supplier tier designation (Tier 1 or Tier 2) based on accumulated review data. 3. PASS: Tier change is recorded with timestamp, acting admin identity, and rationale in the audit trail. 4. PASS: Tier change is reflected immediately on the supplier directory record (EP-07-S01). 5. PASS: Supplier is not notified of internal tier assessment or tier change decision. 6. PASS: Client, coordinator, and guest actors cannot access supplier tier assessment data. 7. FAIL trigger: Tier change is not recorded in audit trail, tier change is not reflected on supplier directory, or supplier is notified of internal tier decision. | F36: Should | G36: B (Francis) | H36: To Do | I36: EP-07-S07 | J36: New-S4; post-event review ratings from New-S5 accumulate before tier decisions. Manual tier upgrade or downgrade by PMCM. Informed by PMCM Internal Supplier Review ratings. | K36: =IF(H36="Done",1,IF(H36="In Progress",0.5,IF(H36="In Review",0.75,0))) -> 0
A37: EP-07 | B37: Supplier Network and Readiness | C37: EP-07-S09 | D37: As a PMCM Admin, I want to review incoming supplier applications and take action on each one, so that prospective suppliers are assessed and added to the network in a controlled process. | E37: 1. PASS: PMCM Admin can access the Supplier Applications inbox from within apps/event; inbox displays all submitted supplier applications. 2. PASS: PMCM Admin can take one of three actions per application: Request Proposal, Schedule Meeting, or Decline. 3. PASS: Approved suppliers (after proposal or meeting) are added to the supplier directory with Pending First Event status (New-S3). 4. PASS: Declined applicants receive a notification of the decision; the declined record is stored with decline reason. 5. PASS: Each action taken on an application produces an audit log entry with timestamp and acting admin identity. 6. PASS: Supplier application data is not accessible to client, coordinator, or guest actors. 7. FAIL trigger: PMCM Admin cannot take action on an application, approved supplier is not added with Pending First Event status, or application data is accessible to non-PMCM actors. | F37: Should | G37: B (Francis) | H37: To Do | I37: EP-07-S06 | J37: New-S2; three action options: Request Proposal, Schedule Meeting, Decline. Approved suppliers added with Pending First Event status (New-S3). Feeds EP-07-S10. | K37: =IF(H37="Done",1,IF(H37="In Progress",0.5,IF(H37="In Review",0.75,0))) -> 0
A38: EP-07 | B38: Supplier Network and Readiness | C38: EP-07-S10 | D38: As a prospective Supplier, I want to check the status of my application after submitting, so that I know where I stand in the onboarding process without contacting PMCM directly. | E38: 1. PASS: Prospective supplier can access a lightweight status page (no full portal login required) to check their application status. 2. PASS: Status page displays one of five statuses: Under Review, Proposal Requested, Meeting Scheduled, Approved, Declined. 3. PASS: Status updates are triggered by PMCM Admin actions in EP-07-S09; status page reflects the current action state without delay. 4. PASS: A confirmation email is sent to the applicant on initial submission (EP-07-S06 trigger). 5. PASS: Status page does not expose other applicant data, internal PMCM notes, or supplier directory data. 6. FAIL trigger: Status page requires full portal login, fewer or more than five statuses are displayed, status does not reflect PMCM Admin actions from EP-07-S09, or internal PMCM data is exposed on the status page. | F38: Should | G38: C (Ethan) | H38: To Do | I38: EP-07-S09 | J38: New-SUP4; five statuses: Under Review, Proposal Requested, Meeting Scheduled, Approved, Declined. Confirmation email sent on submission. Coordinate with Francis (Owner B) on status update triggers from PMCM inbox actions. | K38: =IF(H38="Done",1,IF(H38="In Progress",0.5,IF(H38="In Review",0.75,0))) -> 0
A39: EP-08 -- Finance and Billing
A40: EP-08 | B40: Finance and Billing | C40: EP-08-S01 | D40: As a PMCM Admin, I want a billing statement generated automatically when conforme is signed, so that the 50% downpayment milestone is tracked and invoiced immediately. | E40: 1. PASS: Billing statement is generated automatically on successful conforme upload (EP-04-S01 gate); no manual PMCM Admin action is required to trigger billing statement generation. 2. PASS: Billing statement is handled by BillingOperationsService inside finance-ops. 3. PASS: Generated billing statement includes the 50% downpayment milestone as the first payment record. 4. PASS: recordPayment idempotency guard is enforced; a duplicate conforme upload event does not generate a second billing statement. 5. PASS: Billing statement is retrievable per event by PMCM Admin; not accessible to supplier, coordinator, or guest actors. 6. PASS: PA-109 must be resolved before Done: Anthony must confirm whether uploadConforme calls billing logic directly or routes through FinanceOpsModule. 7. FAIL trigger: Billing statement is not generated automatically on conforme upload, duplicate conforme event generates a second billing statement, billing statement is accessible to non-PMCM non-client actors, or PA-109 is unresolved at Done call. | F40: Must | G40: D (Anthony) | H40: To Do | I40: EP-04-S01 | J40: FR-20; finance-ops; BillingOperationsService; conforme triggers billing. PA-109 OPEN -- Anthony must confirm uploadConforme billing path routing before Done call. ACTION: Anthony to resolve PA-109. | K40: =IF(H40="Done",1,IF(H40="In Progress",0.5,IF(H40="In Review",0.75,0))) -> 0
A41: EP-08 | B41: Finance and Billing | C41: EP-08-S02 | D41: As a PMCM Admin, I want to record and track payment milestones, so that I know whether the 50% balance has been received 7 days before the event. | E41: 1. PASS: PMCM Admin can record payment milestones from within apps/event; up to three configurable payment milestones are supported per event. 2. PASS: Payment milestone tracking is handled via BILLING_READER and PAYMENT_STATUS_READER ports. [PA-101 OPEN: both tokens have no implementations. Anthony must implement before this story can reach In Review.] 3. PASS: A Payment At Risk flag is automatically displayed when the balance payment milestone has not been received 48 hours before the event. 4. PASS: Each recorded payment includes: amount, payment date, payment method, and recording admin identity. 5. PASS: Payment records are accessible to PMCM Admin only; supplier, coordinator, client, and guest actors cannot access payment milestone data. 6. FAIL trigger: More than three milestones are configurable, Payment At Risk flag is not triggered at 48 hours, BILLING_READER or PAYMENT_STATUS_READER ports are bypassed, or PA-101 is unresolved at In Review. | F41: Must | G41: B (Francis) | H41: To Do | I41: EP-08-S01 | J41: FR-92; payment milestones; BILLING_READER; PAYMENT_STATUS_READER tokens. PA-101 OPEN -- Anthony must implement both tokens before EP-08-S02 can reach In Review. ACTION: Anthony to implement tokens. | K41: =IF(H41="Done",1,IF(H41="In Progress",0.5,IF(H41="In Review",0.75,0))) -> 0
A42: EP-08 | B42: Finance and Billing | C42: EP-08-S03 | D42: As a PMCM Admin, I want to add and waive on-site extras billing, so that additional charges from event day are handled with an explicit approval trail. | E42: 1. PASS: PMCM Admin can add on-site extras billing records from within apps/event during or after the event; each extras record is linked to the urgent issue ticket that triggered the extra work (EP-12-S04 upstream trigger). 2. PASS: PMCM Admin can mark an extras record as Waived with a documented reason; the waiver is recorded in Activity History as a deliberate goodwill decision. 3. PASS: Waived extras records are stored and retrievable; the waiver reason is visible to PMCM Admin. 4. PASS: On-site extras billing records are not accessible to supplier, coordinator, or guest actors. 5. PASS: Client can view a summary of on-site extras (including waived items with waiver reason) from within the client portal. 6. FAIL trigger: Extras record is not linked to an urgent issue ticket, waiver is not recorded in Activity History, client cannot view extras summary, or extras data is accessible to non-PMCM non-client actors. | F42: Should | G42: B (Francis) | H42: To Do | I42: EP-12-S04 | J42: FR-21; New-P5; Mark as Waived option with documented reason; linked to urgent issue ticket from EP-12-S04. Recorded in Activity History as deliberate goodwill decision. | K42: =IF(H42="Done",1,IF(H42="In Progress",0.5,IF(H42="In Review",0.75,0))) -> 0
A43: EP-09 -- File and Document Management
A44: EP-09 | B44: File and Document Management | C44: EP-09-S01 | D44: As a PMCM Admin, I want to define file requirements per event, so that suppliers and clients know exactly what documents to submit. | E44: 1. PASS: PMCM Admin can define a file requirements matrix per event from within apps/event after conforme is signed (EP-04-S01 gate). 2. PASS: Each file requirement record captures at minimum: document name, required file type, due date, assigned submitter role (PMCM Admin, Client, or Supplier), and visibility setting. 3. PASS: File requirements are managed by FileRequirementsMatrixService inside file-ops; metadata-only gate is enforced (no real file storage is triggered by this story). 4. PASS: Defined file requirements are visible to the relevant submitter role; PMCM-internal requirements are not exposed to client or supplier. 5. PASS: PMCM Admin can update or remove a file requirement before the due date; the change is reflected immediately in the submitter view. 6. PASS: FILE_REQUIREMENT_READER port is used for read access; FILE_REQUIREMENT_COMMANDS port is used for write access; no direct Prisma calls bypass these ports. 7. PASS: Supplier and client actors can only view their own assigned file requirements; they cannot view requirements assigned to other roles or other events. 8. FAIL trigger: File requirements are definable before conforme, real file storage is triggered by this story, a submitter can view requirements assigned to another role, or direct Prisma calls bypass the port abstraction. | F44: Must | G44: D (Anthony) | H44: To Do | I44: EP-04-S01 | J44: FL-024; file-ops; FileRequirementsMatrixService; metadata-only gate enforced. Signed URLs gated until Anthony approves real storage adapter (PA-106). | K44: =IF(H44="Done",1,IF(H44="In Progress",0.5,IF(H44="In Review",0.75,0))) -> 0
A45: EP-09 | B45: File and Document Management | C45: EP-09-S02 | D45: As a PMCM Admin or Supplier, I want to upload documents to the document vault, so that all event files are centrally stored and traceable. | E45: 1. PASS: PMCM Admin and Supplier can upload documents to the document vault from their respective portals after EP-09-S01 file requirements are defined and EP-15-S03 MIME validation (both Prism scope and Phase 2 phases) is Done. 2. PASS: Upload is processed through DocumentVaultService inside file-ops; MIME type validation (EP-15-S03) runs before any file reaches storage. 3. PASS: Accepted file types are enforced: PDF, DOCX, XLSX, JPG, PNG, MP4, MOV; any other type is rejected with a clear error message before upload completes. 4. PASS: File size limits are enforced per upload. [PLACEHOLDER: confirm per-type or global file size limits -- PA-70 OPEN. Anthony must confirm values.] 5. PASS: Uploaded files are stored with randomized filenames (EP-15-S03 AC item 3); original filename is retained as metadata but is not the storage filename. 6. PASS: Signed upload URLs are used only after Anthony approves the real storage adapter; until adapter approval, upload sessions return a clear unavailable state. 7. PASS: Each uploaded document is associated with its event, submitter identity, submission timestamp, and assigned file requirement (EP-09-S01). 8. PASS: PMCM Admin can view all documents uploaded per event regardless of submitter role; Supplier can only view documents they themselves uploaded or explicitly shared. 9. PASS: Client and guest actors cannot upload to or read from the document vault unless explicitly granted by PMCM Admin per file requirement visibility setting. 10. FAIL trigger: MIME validation is bypassed before file reaches storage, files are stored with original filenames, signed URLs are returned before storage adapter is approved, or supplier can access another supplier uploaded documents. | F45: Must | G45: D (Anthony) | H45: To Do | I45: EP-09-S01, EP-15-S03 | J45: FR-04, FR-32; DocumentVaultService; PA-70 OPEN on file size limits; PA-106 supplier/guest file denial tests deferred. | K45: =IF(H45="Done",1,IF(H45="In Progress",0.5,IF(H45="In Review",0.75,0))) -> 0
A46: EP-10 -- Client Portal
A47: EP-10 | B47: Client Portal | C47: EP-10-S01 | D47: As a Client, I want an action center showing my pending tasks and event status, so that I know what I need to do and when. | E47: 1. PASS: Client action center is accessible from the client portal (apps/client) after conforme is signed (EP-04-S01 gate); not accessible before conforme. 2. PASS: Action center displays the client pending tasks sourced from PrismClientActionCenter contract; no fallback derivation logic remains in the component (fallback must be fully removed before Done). 3. PASS: Each action center card shows at minimum: task name, due date, status, and a clear call-to-action. 4. PASS: Action center does not display PMCM internal cost data, CE rule details, coordinator information, or supplier contract data (FR-33 role boundary). 5. PASS: Action center reflects real-time task status; a task marked complete by PMCM Admin is removed or updated in the client view without requiring a page reload beyond standard polling. 6. PASS: Maxine (Owner A) has reviewed the action center component against the design system before the story moves to Done (FL-020 July decision). 7. PASS: Supplier, coordinator, and guest actors cannot access the client action center or its data payload. 8. FAIL trigger: Fallback derivation logic remains in the component, PMCM internal data is visible in the action center, action center is accessible before conforme, or non-client actors can access the action center payload. | F47: Must | G47: C (Ethan) | H47: In Progress | I47: EP-04-S01 | J47: FL-020; PrismClientActionCenter exists; Partial per File 9; fallback derivation still present -- must be removed. Ethan owns; Maxine reviews per FL-020 July decision. | K47: =IF(H47="Done",1,IF(H47="In Progress",0.5,IF(H47="In Review",0.75,0))) -> 0.5
A48: EP-10 | B48: Client Portal | C48: EP-10-S02 | D48: As a Client, I want to view my event timeline and milestone progress, so that I can track key dates without contacting PMCM directly. | E48: 1. PASS: Client can view an event timeline from within the client portal after conforme is signed. 2. PASS: Timeline displays key milestone dates at minimum: conforme signing date, proposal acceptance date, floor plan approval date, balance payment due date, and event date. 3. PASS: New-CL2 toggle: PMCM Admin can toggle the client event-day view per event; when toggled on, client sees high-level event status only during event day; when toggled off, client sees no live event-day details. 4. PASS: Client event-day view (when toggled on) contains no internal task details, coordinator names or positions, or supplier contract information at any time. 5. PASS: Timeline reflects current milestone completion status; a completed milestone is visually distinguished from a pending milestone. 6. PASS: Supplier, coordinator, and guest actors cannot access the client event timeline. 7. FAIL trigger: Client can view internal task or coordinator details on event day regardless of New-CL2 toggle state, timeline is accessible before conforme, or timeline is accessible to non-client actors. | F48: Should | G48: C (Ethan) | H48: To Do | I48: EP-04-S01 | J48: FR-27; FL-004 thin slice; New-CL2 toggled by PMCM per event. | K48: =IF(H48="Done",1,IF(H48="In Progress",0.5,IF(H48="In Review",0.75,0))) -> 0
A49: EP-10 | B49: Client Portal | C49: EP-10-S03 | D49: As a Client, I want to complete an ocular visit request, so that PMCM can schedule a venue walkthrough before the floor plan is built. | E49: 1. PASS: Client can submit an ocular visit request from within the client portal after conforme is signed (EP-04-S01 gate). 2. PASS: On client submission, a Change Task is automatically created in the PMCM Admin task list with the ocular visit details; no manual PMCM Admin action is required to create the task. 3. PASS: PMCM Admin can view, schedule, and mark the ocular visit task as complete from within apps/event. 4. PASS: Floor plan creation workflow (EP-05-S01) is blocked until the ocular visit task is marked complete by PMCM Admin. PMCM Admin override path confirmed -- PMCM Admin can bypass this gate if ocular visit is never completed. [PA-59 OPEN: Francis and Ms. Mys must confirm override path mechanism before AC item 4 is finalized.] 5. PASS: Client receives a confirmation notification when PMCM Admin marks the ocular visit as scheduled. 6. PASS: Supplier, coordinator, and guest actors cannot access ocular visit request records or Change Task data. 7. FAIL trigger: Change Task is not auto-created on client submission, floor plan workflow is accessible before ocular task is complete and no override path is confirmed, or ocular visit data is accessible to non-PMCM non-client actors. | F49: Should | G49: C (Ethan) | H49: To Do | I49: EP-04-S01 | J49: FR-66; PA-59 OPEN on PMCM override path mechanism. Working assumption: override path exists. Francis and Ms. Mys must confirm mechanism before EP-10-S03 reaches In Review. ACTION: Ask Ms. Mys. | K49: =IF(H49="Done",1,IF(H49="In Progress",0.5,IF(H49="In Review",0.75,0))) -> 0
A50: EP-11 -- Coordinator Experience and Live Ops
A51: EP-11 | B51: Coordinator Experience and Live Ops | C51: EP-11-S01 | D51: As a Coordinator, I want to formally acknowledge my event assignment inside the system, so that PMCM receives my confirmation without relying on Viber. | E51: 1. PASS: Coordinator can view their pending assignment notification inside apps/event after PMCM Admin issues the assignment (EP-02-S05). 2. PASS: Coordinator can acknowledge the assignment with an explicit confirmation action; acknowledgment is recorded in staffing-ops with timestamp and coordinator identity. 3. PASS: On acknowledgment, assignment status on PMCM Admin dashboard transitions from Pending Acknowledgment to Confirmed; PMCM Admin does not need to manually check for acknowledgment. 4. PASS: FR-90 coordinator side: coordinator acknowledgment response is the digital replacement for Viber group chat reconfirmation; no Viber confirmation is required for the system record to reflect a confirmed assignment. 5. PASS: Coordinator cannot acknowledge an assignment that has been withdrawn or replaced; a withdrawn assignment shows a clear status message and the acknowledgment action is unavailable. 6. PASS: Client, supplier, and guest actors cannot access coordinator assignment records or the acknowledgment flow. 7. FAIL trigger: Acknowledgment is not recorded with coordinator identity and timestamp, PMCM Admin dashboard does not update on acknowledgment, coordinator can acknowledge a withdrawn assignment, or non-coordinator actors can access the acknowledgment flow. | F51: Must | G51: B (Francis) | H51: To Do | I51: EP-02-S05 | J51: FR-90 coordinator side; digital replacement for Viber group chat reconfirmation. Depends on EP-02-S05 (PMCM must send assignment before coordinator can respond). | K51: =IF(H51="Done",1,IF(H51="In Progress",0.5,IF(H51="In Review",0.75,0))) -> 0
A52: EP-11 | B52: Coordinator Experience and Live Ops | C52: EP-11-S02 | D52: As a Coordinator, I want to log event-day tasks and urgent issues in real time, so that PMCM has an accurate live record. | E52: 1. PASS: Coordinator can log an event-day task from within apps/event; each task record captures: task description, assigned coordinator, status (Open, In Progress, Complete), and timestamp. 2. PASS: Coordinator can log an urgent issue from within apps/event with one-tap access; urgent issue record captures: issue description, severity, affected area, and timestamp. 3. PASS: Logged urgent issues are immediately visible to PMCM Admin on the live operations dashboard (EP-12-S01) and the Event Day System Operator view (EP-11-S05). 4. PASS: Urgent issue log feeds the additional billing chain (EP-08-S03); each urgent issue is linkable to an on-site extras billing record by PMCM Admin. 5. PASS: Task and urgent issue records are stored in the live-ops module and retrievable per event. 6. PASS: Client, supplier, and guest actors cannot access coordinator task logs or urgent issue records. 7. FAIL trigger: Urgent issue log does not surface immediately on PMCM live ops dashboard, urgent issues are not linkable to billing records, or non-coordinator non-PMCM actors can access task or issue records. | F52: Must | G52: B (Francis) | H52: To Do | I52: EP-02-S05 | J52: live-ops module; event-day task/issue routes. Urgent issue log feeds EP-08-S03 (billing) and EP-12-S04 (EDSO). | K52: =IF(H52="Done",1,IF(H52="In Progress",0.5,IF(H52="In Review",0.75,0))) -> 0
A53: EP-11 | B53: Coordinator Experience and Live Ops | C53: EP-11-S03 | D53: As a Coordinator, I want to mark my attendance and report my arrival, so that PMCM knows which coordinators are on site. | E53: 1. PASS: Coordinator can mark their own attendance status from within apps/event using one of three statuses: Present, Late Arrival, or Absent. 2. PASS: Late Arrival and No Show (Absent with no update) statuses are automatically added to the coordinator profile as reliability notes in the staffing-ops module. 3. PASS: Attendance record is timestamped and includes coordinator identity; PMCM Admin can view attendance status per coordinator per event in real time. 4. PASS: Coordinator can only mark their own attendance; they cannot mark attendance for another coordinator. 5. PASS: Live-ops attendance and replacement routes confirmed Partial per File 9 are fully completed by this story; no stubbed attendance behavior remains. 6. PASS: Client, supplier, and guest actors cannot access coordinator attendance records. 7. FAIL trigger: Late Arrival or No Show is not recorded as a reliability note on the coordinator profile, coordinator can mark another coordinator attendance, or attendance records are accessible to non-PMCM non-coordinator actors. | F53: Must | G53: B (Francis) | H53: To Do | I53: EP-02-S05 | J53: live-ops; attendance/replacement routes; confirmed Partial per File 9. | K53: =IF(H53="Done",1,IF(H53="In Progress",0.5,IF(H53="In Review",0.75,0))) -> 0
A54: EP-11 | B54: Coordinator Experience and Live Ops | C54: EP-11-S04 | D54: As a PMCM Admin, I want to view a real-time coordinator availability and staffing count, so that I can identify staffing gaps before event day. | E54: 1. PASS: PMCM Admin can view a real-time coordinator availability count from within apps/event showing available coordinators per role and skills tag. 2. PASS: A Staffing Gap Warning is automatically displayed when the required coordinator count for an event exceeds the number of confirmed available coordinators for any role. 3. PASS: Availability count reflects current assignment and confirmation status from EP-02-S05 and EP-11-S01; coordinators with Pending Acknowledgment status are not counted as confirmed available. 4. PASS: PMCM Admin can drill into the availability count to see individual coordinator names, roles, and current assignment status. 5. PASS: Availability count and staffing gap data are accessible to PMCM Admin only; coordinator, client, supplier, and guest actors cannot access this view. 6. FAIL trigger: Staffing Gap Warning is not triggered when required count exceeds available count, coordinators with Pending Acknowledgment are counted as confirmed, or availability data is accessible to non-PMCM actors. | F54: Should | G54: B (Francis) | H54: To Do | I54: EP-02-S05 | J54: FR-91; availability count per role and skills tag; Staffing Gap Warning when required count exceeds available coordinators. | K54: =IF(H54="Done",1,IF(H54="In Progress",0.5,IF(H54="In Review",0.75,0))) -> 0
A55: EP-11 | B55: Coordinator Experience and Live Ops | C55: EP-11-S05 | D55: As a Coordinator, I want a role-specific portal view showing only the information relevant to my assigned role, so that I can execute my responsibilities without interface clutter. | E55: ROLE VIEW 1 -- Floor Director and Stage Director (New-CO2): 1. PASS: Floor Director and Stage Director role view displays: role badge, event details, briefing documents, assigned task list, and communication thread scoped exclusively to Event Day System Operator and Ms. Mys. 2. PASS: Communication thread is not accessible to any other coordinator role, client, supplier, or guest actor. ROLE VIEW 2 -- Registration Staff (New-CO3): 3. PASS: Registration Staff role view is laptop-optimized; the layout and controls are designed for desktop use, not mobile. 4. PASS: Role view displays a searchable guest masterlist with a Check In button per guest, a Walk-In Addition button, and a Flag for Verification control for unauthorized walk-ins. 5. PASS: Real-time attendance count is visible and updates without requiring a manual refresh. ROLE VIEW 3 -- Ingress and Egress Assistant (New-CO4): 6. PASS: Ingress and Egress Assistant role view displays: role badge, supplier schedule, and three status buttons per supplier: Arrived, Set Up and Ready, Done and Leaving. 7. PASS: Verified toggle and photo upload per status update are present and functional. 8. PASS: Late Arrival flag appears automatically at exactly 15 minutes past the scheduled supplier window; the flag does not appear before the 15-minute threshold. ROLE VIEW 4 -- Event Day System Operator (New-CO5): 9. PASS: Event Day System Operator role view displays on laptop: full event task dashboard, supplier status overview, coordinator check-in section, urgent issue log with one-tap access, task reassignment tool, wrap-up screen access, and real-time attendance feed. 10. PASS: Task reassignment tool notifies Ms. Mys on reassignment action; auto-approval fires after exactly 2 minutes if Ms. Mys does not respond. ROLE VIEW 5 -- Usher and General Coordinator (New-CO6): 11. PASS: Usher and General Coordinator role view displays: role badge, simple instruction list with post and responsibilities, and an urgent issue button; no other controls or data are present. 12. PASS: Interface is minimal; no task management controls, coordinator directory data, or supplier information is visible in this role view. CROSS-ROLE RULES: 13. PASS: Each coordinator only sees the role view matching their assigned role for the event; a coordinator assigned as Registration Staff cannot access the Event Day System Operator view. 14. PASS: Client, supplier, and guest actors cannot access any coordinator role view. 15. PASS: Break-down trigger is monitored at every cadence boundary; if any single role view is Done while others are Blocked or In Progress, this story is immediately moved to the AC Detail tab with per-role-view rows. 16. FAIL trigger: Any role view exposes data outside its defined scope, a coordinator can access a role view other than their assigned role, Late Arrival flag fires before or after the 15-minute threshold, communication thread in New-CO2 is accessible to actors outside Event Day System Operator and Ms. Mys, or auto-approval fires before 2 minutes. | F55: Must | G55: B (Francis) | H55: To Do | I55: EP-02-S05 | J55: New-C1, New-CO1 through New-CO6; all coordinator role views in apps/event. BUILD PLAN LOCKED: Option A (separate components). Build sequence: 1) Event Day System Operator, 2) Registration Staff, 3) Floor Director and Stage Director, 4) Ingress and Egress Assistant, 5) Usher and General Coordinator. Shared elements (role badge, urgent issue button, event details header) extracted to packages/ui first. BREAK-DOWN TRIGGER: if any single role view Done while others stuck, move to AC Detail tab immediately. | K55: =IF(H55="Done",1,IF(H55="In Progress",0.5,IF(H55="In Review",0.75,0))) -> 0
A56: EP-12 -- Event Day Operations
A57: EP-12 | B57: Event Day Operations | C57: EP-12-S01 | D57: As a PMCM Admin, I want a live operations dashboard showing real-time supplier status, coordinator positions, and guest attendance, so that I can manage event day from a single view. | E57: 1. PASS: Live operations dashboard is accessible to PMCM Admin from within apps/event during an active event; confirmed Partial per File 9. 2. PASS: Dashboard displays in real time: supplier on-site status per category (from EP-07-S05), coordinator positions and attendance status (from EP-11-S03), and guest attendance count (from EP-13-S01 and EP-13-S02). 3. PASS: Dashboard is mobile-first and phone-friendly; PMCM Admin can use it on a phone on event day; laptop is the primary command station but mobile must be functional. 4. PASS: Dashboard data refreshes in real time without requiring manual reload; a supplier status update or coordinator attendance mark is reflected on the dashboard within a reasonable latency window. 5. PASS: Dashboard feeds EP-12-S06 (AI Event Day Copilot) data streams; the data available on the dashboard is the same data polled by the Copilot agent. 6. PASS: Client, supplier (beyond their own status), coordinator (beyond their own role view), and guest actors cannot access the live operations dashboard or its data payload. 7. PASS: Attendance count displayed on the dashboard matches the real-time count updated by coordinator check-in actions (EP-13-S01) and guest self-service check-in (EP-13-S02). 8. FAIL trigger: Dashboard does not reflect real-time updates, mobile rendering is broken or unusable, supplier status or coordinator attendance data is inaccessible, or non-PMCM actors can access dashboard data. | F57: Must | G57: B (Francis) | H57: In Progress | I57: EP-06-S03 | J57: FR-05; live-ops module; confirmed Partial per File 9. Mobile-first phone-friendly. Feeds EP-12-S06 AI Copilot. | K57: =IF(H57="Done",1,IF(H57="In Progress",0.5,IF(H57="In Review",0.75,0))) -> 0.5
A58: EP-12 | B58: Event Day Operations | C58: EP-12-S02 | D58: As a PMCM Admin, I want to trigger PARE for emergency supplier replacement, so that a withdrawn supplier can be replaced within the change freeze window. | E58: 1. PASS: PMCM Admin can trigger PARE from within apps/event when a supplier withdrawal is received during the change freeze window (EP-06-S03 and EP-12-S03 prerequisites). 2. PASS: PARE is handled by PAREService inside the ai-governance module; the 5-agent orchestrator runs within ai-governance and does not mutate supplier or event records directly. 3. PASS: DataSanitizer runs on all supplier and event data before it is passed to the Claude API; no PII reaches the API in unsanitized form. Supplier names replaced with Supplier X - Production; contact numbers and emails removed entirely. 4. PASS: ZDR is confirmed active (EP-15-S05 must be Done before this story moves to In Progress); no PARE run proceeds without ZDR confirmation. 5. PASS: PARE generates a prioritized replacement recommendation with rationale; the recommendation is presented to PMCM Admin for review before any action is taken. 6. PASS: PMCM Admin must explicitly approve the replacement recommendation before any replacement notification is sent to suppliers; no automated replacement occurs without PMCM Admin confirmation (human approval gate). 7. PASS: Every PARE run produces an AIAuditLog entry recording: run timestamp, triggering event ID, sanitized input summary, recommendation output, and PMCM Admin approval or rejection decision. 8. PASS: PARE is described and functions as an assistive tool; no AC criterion implies PARE manages supplier replacement autonomously or replaces PMCM Admin judgment. 9. PASS: Supplier is unaware of PARE involvement; all supplier-facing communications are reviewed and sent by PMCM Admin through the standard FR-37 supplier confirmation flow. 10. PASS: Client, coordinator, and guest actors cannot access PARE outputs, recommendations, or AIAuditLog entries. 11. FAIL trigger: PARE takes any action without explicit PMCM Admin approval, unsanitized PII reaches the Claude API, AIAuditLog entry is absent for any PARE run, ZDR is not confirmed before PARE runs, or PARE outputs are accessible to non-PMCM actors. | F58: Must | G58: D (Anthony) | H58: To Do | I58: EP-06-S03, EP-12-S03, EP-15-S05 | J58: FR-AI-04; ai-governance module; PAREService; 5-agent orchestrator. PA-75 OPEN on Agentic scope tag cadence mapping. BLOCKED on EP-15-S05 (ZDR gate). Cannot move to In Progress until EP-15-S05 Done. | K58: =IF(H58="Done",1,IF(H58="In Progress",0.5,IF(H58="In Review",0.75,0))) -> 0
A59: EP-12 | B59: Event Day Operations | C59: EP-12-S03 | D59: As a Supplier, I want to withdraw from an event and submit a reason, so that PMCM is formally notified and can initiate replacement. | E59: 1. PASS: Supplier can submit a withdrawal from an event from within the supplier portal (apps/supplier); withdrawal form captures a mandatory reason field. 2. PASS: Withdrawal is handled by OpsEventSupplierWithdrawalController inside supplier-ops; requireSupplierAdmin policy is enforced. 3. PASS: PMCM Admin receives a notification on supplier withdrawal; withdrawal record is visible on the event supplier status view. 4. PASS: If withdrawal occurs within the change freeze window (5 days before event), the withdrawal automatically triggers Emergency Change classification and makes PARE activation available to PMCM Admin (EP-12-S02). 5. PASS: Supplier can only withdraw from events they are confirmed as assigned to; they cannot submit withdrawal for another supplier or an event they are not assigned to. 6. PASS: Withdrawal record is stored with timestamp, supplier identity, reason, and whether it occurred inside or outside the change freeze window. 7. PASS: Client, coordinator, and guest actors cannot submit withdrawal actions or access withdrawal records. 8. FAIL trigger: Withdrawal is submittable without a reason, requireSupplierAdmin policy is not enforced, withdrawal within freeze window does not trigger Emergency Change classification, or withdrawal records are accessible to non-PMCM non-supplier actors. | F59: Must | G59: C (Ethan) | H59: Done | I59: EP-06-S03 | J59: supplier-ops; OpsEventSupplierWithdrawalController; requireSupplierAdmin policy; confirmed Live per File 9. | K59: =IF(H59="Done",1,IF(H59="In Progress",0.5,IF(H59="In Review",0.75,0))) -> 1
A60: EP-12 | B60: Event Day Operations | C60: EP-12-S04 | D60: As a Coordinator (Event Day System Operator), I want to log urgent issues, reassign tasks, and mark coordinator attendance during the event, so that PMCM has a real-time operational record and can respond immediately. | E60: 1. PASS: Event Day System Operator can log urgent issues with one-tap access from their role view (EP-11-S05 New-CO5); each issue record captures: description, severity, affected area, and timestamp. 2. PASS: Event Day System Operator can reassign a task to another coordinator from the task dashboard; reassignment triggers an immediate notification to Ms. Mys via notification-ops module. 3. PASS: If Ms. Mys does not respond to the reassignment notification within exactly 2 minutes, the reassignment is auto-approved; auto-approval is recorded with timestamp and auto-approval reason. 4. PASS: Event Day System Operator can mark coordinator attendance as Present, Late Arrival, or Absent from the coordinator check-in section of their role view. 5. PASS: Late Arrival and No Show (Absent) attendance marks are automatically written to the coordinator reliability notes in staffing-ops (confirm write path with Anthony before AC sign-off). 6. PASS: Urgent issues logged here feed the additional billing chain (EP-08-S03); each urgent issue is linkable to an on-site extras billing record. 7. PASS: All actions (issue log, task reassignment, attendance mark) produce audit log entries. 8. PASS: Client, supplier, and guest actors cannot access Event Day System Operator controls, urgent issue records, or coordinator attendance data. 9. FAIL trigger: Auto-approval fires before 2 minutes, Ms. Mys notification is not triggered on reassignment, reliability notes are not written on Late Arrival or No Show, urgent issues are not linkable to billing records, or non-PMCM non-coordinator actors can access these records. | F60: Must | G60: B (Francis) | H60: To Do | I60: EP-12-S01 | J60: New-C3, New-C4; Owner B builds coordinator-facing trigger surface in apps/event. Owner D owns notification-ops module for Ms. Mys phone notification -- coordinate before In Review. Reliability notes written by staffing-ops -- confirm write path with Anthony before AC sign-off. | K60: =IF(H60="Done",1,IF(H60="In Progress",0.5,IF(H60="In Review",0.75,0))) -> 0
A61: EP-12 | B61: Event Day Operations | C61: EP-12-S05 | D61: As a PMCM Admin, I want to build and configure in-event engagement games, so that guests can participate during the event without requiring an app download. | E61: 1. PASS: PMCM Admin can create and configure in-event engagement games from within apps/event after conforme is signed (EP-04-S01 gate). 2. PASS: Exactly five pre-built game templates are available: Live Poll, Word Cloud, Ice Breaker Quiz, Raffle Draw, and Open Q and A. 3. PASS: Each game is configurable per event: PMCM Admin can set game title, questions or options, and participation window. 4. PASS: Each configured game generates a QR code that links to the guest participation page (EP-13-S07); the QR code is displayable on the LED wall. 5. PASS: Game participation does not require guests to download an app or create an account; QR code opens a web page in the guest phone browser. 6. PASS: PMCM Admin can activate and deactivate games during the event; deactivated games do not accept new responses. 7. PASS: Game response data is stored per event and retrievable by PMCM Admin after the event closes. 8. FAIL trigger: Fewer or more than five game templates are available, QR code does not generate per configured game, game requires app download or account creation, or game responses are not stored per event. | F61: Could | G61: B (Francis) | H61: To Do | I61: EP-04-S01 | J61: FR-40; Phase 2 scope; five pre-built templates. Generates QR code linking to EP-13-S07. | K61: =IF(H61="Done",1,IF(H61="In Progress",0.5,IF(H61="In Review",0.75,0))) -> 0
A62: EP-12 | B62: Event Day Operations | C62: EP-12-S06 | D62: As an Event Day System Operator, I want an AI monitoring agent watching all live ops data streams and surfacing prioritized alerts every 60 seconds, so that I can respond to supplier late arrivals, overdue tasks, coordinator no-shows, and check-in anomalies before they escalate. | E62: 1. PASS: AI monitoring agent polls all live ops data streams (EP-12-S01) at exactly 60-second intervals during an active event only; polling does not occur outside event day hours. 2. PASS: Agent is powered by the Haiku model within ai-governance; DataSanitizer runs on all live ops data before each API call. 3. PASS: Agent surfaces prioritized alerts covering: supplier late arrivals, overdue tasks, coordinator no-shows, and check-in anomalies; alert priority is ranked with highest-risk items first. 4. PASS: ZDR is confirmed active before this feature is deployed. 5. PASS: Alerts are surfaced to the Event Day System Operator and PMCM Admin as assistive alerts only; no action is taken on any alert without explicit PMCM Admin confirmation. 6. PASS: Human approval gate is present: every recommended response to an alert requires explicit PMCM Admin confirmation before execution; no automated response fires. 7. PASS: Every poll cycle that produces at least one recommendation generates an AIAuditLog entry recording: poll timestamp, event ID, sanitized data summary, alerts generated, and PMCM Admin response to each alert. 8. PASS: Live ops data feed availability is confirmed with Francis (Owner B) before story moves to In Progress; agent must read from the same data streams as EP-12-S01. 9. PASS: AI Copilot alerts are accessible to Event Day System Operator and PMCM Admin only; client, supplier, coordinator (beyond own role view), and guest actors cannot access Copilot output. 10. FAIL trigger: Agent polls outside active event hours, any alert triggers automated action without explicit PMCM Admin confirmation, DataSanitizer bypassed on any poll cycle, AIAuditLog entry absent for recommendation-producing poll cycle, or Copilot output accessible to non-PMCM non-EDSO actors. | F62: Should | G62: D (Anthony) | H62: To Do | I62: EP-12-S01, EP-15-S05 | J62: FR-AI-07; Haiku model; Agentic scope. Reclassified from C3 to C4 -- dual-gated on EP-12-S01 and EP-15-S05. Coordinate with Francis (Owner B) on live ops dashboard data feed before In Progress. | K62: =IF(H62="Done",1,IF(H62="In Progress",0.5,IF(H62="In Review",0.75,0))) -> 0
A63: EP-13 -- Guest Experience and Digital Registration
A64: EP-13 | B64: Guest Experience and Digital Registration | C64: EP-13-S01 | D64: As a Coordinator (Registration Staff), I want a laptop-optimized guest masterlist with check-in, walk-in addition, and flag for verification controls, so that guest attendance is recorded accurately from the coordinator side. | E64: 1. PASS: Guest masterlist is accessible to Registration Staff coordinators from within apps/event on a laptop; the view is optimized for desktop use (New-CO3). 2. PASS: Masterlist is searchable by guest name; search returns results in real time without full page reload. 3. PASS: Registration Staff can mark a guest as checked in using a Check In button per guest row; checked-in status is recorded with timestamp and coordinator identity. 4. PASS: Registration Staff can add a walk-in guest using a Walk-In Addition button; walk-in record captures guest name and is added to the masterlist immediately. 5. PASS: Registration Staff can flag a guest or walk-in for verification using a Flag for Verification control; flagged records are visually distinguished in the masterlist. 6. PASS: Real-time attendance count is visible on the masterlist view and updates on every check-in or walk-in addition without requiring a manual refresh. 7. PASS: Attendance count feeds the live operations dashboard (EP-12-S01) in real time. 8. PASS: Client, supplier, and guest actors cannot access the coordinator guest masterlist or its data. 9. FAIL trigger: Masterlist is not searchable, real-time attendance count does not update on check-in or walk-in, walk-in addition is not immediately reflected in the masterlist, or non-coordinator non-PMCM actors can access masterlist data. | F64: Must | G64: B (Francis) | H64: To Do | I64: EP-04-S01 | J64: New-CO3; apps/event coordinator surface; laptop-optimized. Distinct from guest self-service check-in (EP-13-S02). | K64: =IF(H64="Done",1,IF(H64="In Progress",0.5,IF(H64="In Review",0.75,0))) -> 0
A65: EP-13 | B65: Guest Experience and Digital Registration | C65: EP-13-S02 | D65: As a Guest, I want to check in at the event by providing my name or through headcount-only mode, so that my attendance is recorded without requiring an app download or account. | E65: 1. PASS: Guest can check in by providing their name on the guest check-in page (apps/guest) without creating an account or downloading an app. 2. PASS: Name search matches against the pre-loaded guest masterlist; a matched guest is checked in with one confirmation action. 3. PASS: Headcount-only mode is available; in this mode, attendance is recorded as an increment to a running count without capturing individual guest names. 4. PASS: Walk-in policy per New-CL1 (private events under 200 pax) is enforced: if the client event is configured as private under 200 pax, unregistered walk-ins trigger a flag for verification rather than automatic check-in. 5. PASS: Real-time attendance count is updated on every guest check-in and feeds the live operations dashboard (EP-12-S01) and coordinator masterlist (EP-13-S01). 6. PASS: No app download or account creation is required at any point in the guest check-in flow. 7. PASS: Guest check-in data is accessible to PMCM Admin and Registration Staff coordinators only; individual guest names are not exposed to supplier or other guest actors. 8. FAIL trigger: Guest check-in requires account creation or app download, headcount-only mode is absent, walk-in policy enforcement is absent for private events under 200 pax, or real-time count does not feed live ops dashboard. | F65: Must | G65: C (Ethan) | H65: In Progress | I65: EP-04-S01 | J65: FR-39, FR-95; apps/guest; name-based check-in and walk-in flagging confirmed Partial per File 9. Remaining: headcount-only mode, walk-in policy enforcement, real-time count feed. | K65: =IF(H65="Done",1,IF(H65="In Progress",0.5,IF(H65="In Review",0.75,0))) -> 0.5
A66: EP-13 | B66: Guest Experience and Digital Registration | C66: EP-13-S03 | D66: As a Guest, I want to check in at the event by scanning a QR code, so that high-volume events can be processed quickly. | E66: 1. PASS: Guest can scan a QR code displayed at the event venue using their own phone camera or browser to initiate check-in; no app download required. 2. PASS: QR scan requires HTTPS; the check-in page is served over HTTPS and does not function over HTTP. 3. PASS: QR check-in records the same attendance data as name-based check-in (EP-13-S02); no separate attendance record type is created for QR check-ins. 4. PASS: If the client provided guest email addresses, QR code is associated with a specific guest record (FR-39); QR check-in matches the guest to their masterlist entry. 5. PASS: Manual name search remains available as a fallback on laptop if QR scanning is unavailable. 6. PASS: Real-time attendance count updates on QR check-in identically to name-based check-in. 7. FAIL trigger: QR check-in requires app download, page is served over HTTP, QR check-in creates a separate attendance record type, or real-time count does not update on QR check-in. | F66: Should | G66: C (Ethan) | H66: Blocked | I66: EP-13-S02 | J66: FR-39, FR-95; QR mode. BLOCKED: PA-63 and PA-66 OPEN on whether guest self-scan falls under same QR/camera gate as coordinator check-in. Unblock: resolve PA-63 and PA-66 at C3 start (July 6). If unresolved by July 10, declare post-July. HTTPS required. | K66: =IF(H66="Done",1,IF(H66="In Progress",0.5,IF(H66="In Review",0.75,0))) -> 0
A67: EP-13 | B67: Guest Experience and Digital Registration | C67: EP-13-S04 | D67: As a Guest, I want to submit a star rating, text review, and media upload after the event, so that PMCM and the client can review my experience. | E67: 1. PASS: Guest feedback form is accessible after the event closes; guest does not need an account to submit feedback. 2. PASS: Feedback form captures: star rating (1 to 5), text review, and optional media upload (video max 60 seconds per New-EX2). 3. PASS: All feedback submissions go to a PMCM moderated review queue before any use; feedback is never auto-published. 4. PASS: Client permission is explicitly required before PMCM uses or shares any guest feedback publicly; no feedback is shared without documented client permission. 5. PASS: PMCM Admin can view all feedback in the moderated queue and take action (approve for sharing, reject, or hold). 6. PASS: Guest feedback records are not accessible to supplier, coordinator, or other guest actors. 7. FAIL trigger: Feedback is auto-published without PMCM moderation, client permission is not required before public use, video upload exceeds 60 seconds without rejection, or feedback data is accessible to non-PMCM non-client actors. | F67: Should | G67: C (Ethan) | H67: To Do | I67: EP-04-S01 | J67: FR-41, New-EX2; Phase 2 scope; video upload max 60 seconds; all submissions go to PMCM moderated review queue; client permission required before any public use; never auto-published. | K67: =IF(H67="Done",1,IF(H67="In Progress",0.5,IF(H67="In Review",0.75,0))) -> 0
A68: EP-13 | B68: Guest Experience and Digital Registration | C68: EP-13-S05 | D68: As a PMCM Admin, I want to record the digital registration platform details and import final headcount data after the event, so that registration records are reconciled for large events. | E68: 1. PASS: PMCM Admin can record digital registration platform details per event from within apps/event; record captures: platform name (XPERTO or client-chosen alternative), platform contact, and setup confirmation status. 2. PASS: Digital Registration supplier sub-ticket tracks platform setup confirmation; sub-ticket is linked to the relevant supplier category record. 3. PASS: PMCM Admin can import final headcount data from the external platform after the event; imported headcount is stored per event as the reconciled attendance count. 4. PASS: PRISM does not handle ticket sales or payment processing at any point in this flow; no AC criterion implies PRISM processes guest payments or manages ticket inventory. 5. PASS: This feature is scoped to events with 200 to 250 pax and above using XPERTO or a client-chosen digital registration platform; smaller events are not required to use this flow. 6. PASS: Imported headcount data is visible to PMCM Admin; client can view final reconciled headcount for their event; supplier and guest actors cannot access platform details or headcount import records. 7. FAIL trigger: PRISM processes ticket sales or payments, feature is applied to events below 200 pax threshold without PMCM Admin override, headcount import data is accessible to supplier or guest actors, or digital registration sub-ticket is not linked to a supplier category record. | F68: Must | G68: B (Francis) | H68: To Do | I68: EP-04-S01 | J68: New-GU1; scoped to 200-250 pax and above using XPERTO; PRISM does not handle ticket sales or payment processing. | K68: =IF(H68="Done",1,IF(H68="In Progress",0.5,IF(H68="In Review",0.75,0))) -> 0
A69: EP-13 | B69: Guest Experience and Digital Registration | C69: EP-13-S06 | D69: As a Guest, I want to open a web page via QR on the LED wall without downloading an app, so that I can access event information instantly. | E69: 1. PASS: A QR code is generated per event that links to a guest-accessible web page (apps/guest); QR code is displayable on the LED wall. 2. PASS: Guest can open the web page by scanning the QR code with their phone camera; no app download or account creation is required. 3. PASS: Web page is served over HTTPS; it does not function over HTTP. 4. PASS: Web page displays relevant event information accessible to guests without authentication. 5. PASS: Web page does not expose internal PMCM data, coordinator details, supplier information, or billing data. 6. FAIL trigger: Web page requires app download or account creation, page is served over HTTP, or internal PMCM data is exposed on the guest page. | F69: Could | G69: C (Ethan) | H69: To Do | I69: None | J69: FR-40; no account required; HTTPS required; Phase 2 scope. | K69: =IF(H69="Done",1,IF(H69="In Progress",0.5,IF(H69="In Review",0.75,0))) -> 0
A70: EP-13 | B70: Guest Experience and Digital Registration | C70: EP-13-S07 | D70: As a Guest, I want to access and participate in event games via QR code on my phone browser, so that I can engage with the event without downloading an app or creating an account. | E70: 1. PASS: Guest can access the game participation page by scanning the QR code generated by EP-12-S05; no app download or account required. 2. PASS: Game participation page is served over HTTPS. 3. PASS: Guest can participate in the active configured game template (Live Poll, Word Cloud, Ice Breaker Quiz, Raffle Draw, or Open Q and A). 4. PASS: Guest responses are recorded per game session and stored for PMCM Admin review after the event. 5. PASS: Guest participation page does not expose internal event data, other guests responses, or PMCM operational data. 6. FAIL trigger: App download or account required, page served over HTTP, guest responses not stored, or internal PMCM data exposed on participation page. | F70: Could | G70: C (Ethan) | H70: Blocked | I70: EP-12-S05 | J70: FR-40; apps/guest; Phase 2 scope. BLOCKED: QR/camera gate; same gate as EP-13-S03. PA-63 and PA-66 OPEN. Depends on EP-12-S05 (game must be built first). If PA-63 and PA-66 unresolved by July 10, declare post-July. | K70: =IF(H70="Done",1,IF(H70="In Progress",0.5,IF(H70="In Review",0.75,0))) -> 0
A71: EP-14 -- Closure and Archive
A72: EP-14 | B72: Closure and Archive | C72: EP-14-S01 | D72: As a PMCM Admin, I want to archive a completed event and generate post-event insights, so that the event record is preserved and learnings are captured. | E72: 1. PASS: PMCM Admin can initiate event archiving from within apps/event after the event date has passed and EP-12-S01 (live ops) is complete; archiving is not available during an active event. 2. PASS: Archive action is handled by closure-ops module; close-gate readiness check runs before archiving proceeds and blocks if required post-event conditions are not met. 3. PASS: Client actor cannot trigger event archiving under any circumstance; archive command is PMCM Admin only. 4. PASS: New-SY1 Post-Event Wrap-Up Screen is present: PMCM Admin sees a structured wrap-up screen summarizing event completion status before confirming archive. 5. PASS: New-SY2 One-Screen Close is present: the final archive confirmation is completable in a single screen action without multi-step navigation. 6. PASS: Deterministic Event Insights Card (New-P2) is generated on archive: a structured summary of event outcomes (attendance count, task completion rate, supplier performance summary, urgent issues count) is produced from existing system records without AI. 7. PASS: AI-enhanced insights (FR-AI-08 PEIL) are explicitly not generated here; Event Insights Card is populated with deterministic data only; AI upgrade is EP-16-S06 scope gated on EP-15-S05. 8. PASS: Archived event record is preserved in full and retrievable by PMCM Admin; no data is deleted on archive. 9. PASS: Archive event produces an audit log entry recording the archiving admin identity, timestamp, and event ID. 10. FAIL trigger: Client can trigger archiving, archive proceeds without close-gate readiness check passing, Event Insights Card uses AI-generated content before EP-15-S05 is Done, archived record is not fully retrievable, or audit log entry is absent on archive. | F72: Must | G72: B (Francis) | H72: In Progress | I72: EP-12-S01 | J72: FL-013; closure-ops; archive commands confirmed Partial per File 9. Close gates, archive guard, and deterministic Event Insights confirmed. PA-89 OPEN on FL cross-reference. | K72: =IF(H72="Done",1,IF(H72="In Progress",0.5,IF(H72="In Review",0.75,0))) -> 0.5
A73: EP-14 | B73: Closure and Archive | C73: EP-14-S02 | D73: As a PMCM Admin, I want to complete and file all post-event documents, so that the event record is compliant and retrievable. | E73: 1. PASS: PMCM Admin can access the post-event documentation submission tracker from within apps/event after an event is archived (EP-14-S01 gate). 2. PASS: Tracker displays all required post-event documents with their submission status (Pending, Submitted, Overdue). 3. PASS: PMCM Admin can submit or upload each required post-event document against its tracker entry; submission records timestamp and submitting admin identity. 4. PASS: A 3 to 5 day endorsement window is enforced; documents not submitted within the window trigger a Deadline Overdue alert on the PMCM command surface. 5. PASS: Client can acknowledge receipt of post-event documents from within the client portal; acknowledgment is recorded with timestamp. 6. PASS: PMCM Admin receives a notification when the client acknowledges receipt. 7. PASS: Completed and filed post-event documents are retrievable per event by PMCM Admin; documents are not accessible to supplier, coordinator, or guest actors. 8. FAIL trigger: Deadline Overdue alert is not triggered within the endorsement window, client cannot acknowledge receipt, or post-event documents are accessible to non-PMCM non-client actors. | F73: Should | G73: B (Francis) | H73: To Do | I73: EP-14-S01 | J73: FR-04, FR-32; closure-ops; post-event document completion. 3 to 5 day endorsement window enforced. | K73: =IF(H73="Done",1,IF(H73="In Progress",0.5,IF(H73="In Review",0.75,0))) -> 0
A74: EP-15 -- Security, Privacy, and Auth
A75: EP-15 | B75: Security, Privacy, and Auth | C75: EP-15-S01 | D75: As a PMCM Admin, I want mandatory 2FA via TOTP with lockout and session controls, so that unauthorized access to the PMCM Admin account is prevented. | E75: 1. PASS: 2FA is mandatory for all PMCM Admin accounts via TOTP only; no alternative 2FA method is available for PMCM Admin. 2. PASS: Account is locked after 5 consecutive failed login attempts; lockout duration is exactly 10 minutes. 3. PASS: Password reset link expires in exactly 15 minutes after issuance. 4. PASS: Session timeout is configurable per role by PMCM Admin. 5. PASS: Minimum password requirements are enforced. [PLACEHOLDER: specific length and complexity values pending PA-69 resolution. Anthony and Ms. Mys must confirm before AC is finalized.] 6. PASS: 2FA setup is required before PMCM Admin can access any protected surface; no bypass path exists. 7. FAIL trigger: 2FA is optional for PMCM Admin, lockout does not trigger after 5 failures, lockout duration is not exactly 10 minutes, password reset link does not expire at 15 minutes, or a bypass path exists for 2FA. | F75: Must | G75: D (Anthony) | H75: Done | I75: None | J75: New-SEC1; 2FA mandatory for PMCM Admin via TOTP only; lockout after 5 consecutive failures with 10-minute cooldown; password reset link expires in 15 minutes; session timeout configurable per role. PA-69 OPEN -- minimum password requirements not yet confirmed. | K75: =IF(H75="Done",1,IF(H75="In Progress",0.5,IF(H75="In Review",0.75,0))) -> 1
A76: EP-15 | B76: Security, Privacy, and Auth | C76: EP-15-S02 | D76: As a PMCM Admin, I want a privacy and PII management layer including consent tracking and data subject rights handling, so that the system complies with data protection obligations. | E76: 1. PASS: Privacy Notice is shown on first login to all users across all portals; users cannot proceed without acknowledging the notice. 2. PASS: Data export function is available for right-to-access requests; PMCM Admin can export all personal data associated with a specific data subject. 3. PASS: Anonymization function is available for right-to-erasure requests; PMCM Admin can anonymize a data subject record with a single action. 4. PASS: Data retention is configurable per data type by PMCM Admin. 5. PASS: Personal Information Inventory is visible to PMCM Admin only. [PLACEHOLDER: confirm whether read-only report view or editable/annotatable -- PA-72 OPEN. Ms. Mys must confirm.] 6. PASS: Privacy controls are not accessible to client, supplier, coordinator, or guest actors. 7. FAIL trigger: Privacy Notice is not shown on first login to any portal, data export or anonymization functions are absent, or Personal Information Inventory is accessible to non-PMCM actors. | F76: Must | G76: D (Anthony) | H76: Done | I76: None | J76: New-SEC2; Privacy Notice on first login to all users; data export for right-to-access; anonymization for right-to-erasure; retention configurable per data type. PA-72 OPEN -- Personal Information Inventory read-only or editable must be confirmed by Ms. Mys. | K76: =IF(H76="Done",1,IF(H76="In Progress",0.5,IF(H76="In Review",0.75,0))) -> 1
A77: EP-15 | B77: Security, Privacy, and Auth | C77: EP-15-S03 | D77: As a platform maintainer, I want MIME type validation enforced on all file uploads, so that only accepted file types reach storage. | E77: 1. PASS: MIME type checking is performed on all file uploads using actual MIME type detection, not file extension only. 2. PASS: Accepted file types are enforced: PDF, DOCX, XLSX, JPG, PNG, MP4, MOV; any other type is rejected before upload completes. 3. PASS: All uploaded files are stored with randomly generated filenames; original filename is retained as metadata only. 4. PASS: Prism scope phase: MIME validation and random filename enforcement are implemented and active. 5. PASS: Phase 2 scope: file size limits are enforced per upload. [PLACEHOLDER: confirm per-type or global file size limits -- PA-70 OPEN. Anthony must confirm values before Phase 2 AC is finalized.] 6. FAIL trigger: MIME type is checked by extension only, any file type outside the accepted list reaches storage, files are stored with original filenames, or file size limits are not enforced after Phase 2 scope is active. | F77: Must | G77: D (Anthony) | H77: To Do | I77: None | J77: New-SEC3; MIME type checking (not extension only); accepted types: PDF, DOCX, XLSX, JPG, PNG, MP4, MOV; files stored with randomly generated names. PA-70 OPEN on file size limits for Phase 2 scope. | K77: =IF(H77="Done",1,IF(H77="In Progress",0.5,IF(H77="In Review",0.75,0))) -> 0
A78: EP-15 | B78: Security, Privacy, and Auth | C78: EP-15-S04 | D78: As Ms. Mys or EA, I want an append-only tamper-resistant audit trail recording every system action, so that all activity is traceable and unalterable. | E78: 1. PASS: Every action in the system produces an audit log entry recorded in the trust-ops module (ops_audit_logs table); no action type is excluded from the audit trail. 2. PASS: Audit trail is append-only and tamper-resistant; no actor can edit, delete, or overwrite an existing audit log entry. 3. PASS: Each audit log entry records at minimum: timestamp, user identity, role, action type, and affected data. 4. PASS: Audit trail is accessible only to Ms. Mys and EA; no other actor can access the audit trail under any circumstance. 5. PASS: Audit trail is filterable by: user, event, date range, and action type. 6. PASS: PA-71 must be resolved before Done: Ms. Mys must confirm EA full role name and whether EA has own system login or is a sub-role under PMCM Admin. 7. FAIL trigger: Any action type is excluded from the audit trail, any actor other than Ms. Mys and EA can access the audit trail, audit entries are editable or deletable, or PA-71 is unresolved at Done call. | F78: Must | G78: D (Anthony) | H78: To Do | I78: None | J78: New-SEC4; trust-ops; AuditService; append-only and tamper-resistant; accessible ONLY to Ms. Mys and EA. PA-71 OPEN on EA role definition. ACTION: Ask Ms. Mys. | K78: =IF(H78="Done",1,IF(H78="In Progress",0.5,IF(H78="In Review",0.75,0))) -> 0
A79: EP-15 | B79: Security, Privacy, and Auth | C79: EP-15-S05 | D79: As a PMCM Admin, I want ZDR confirmed and DataSanitizer enforced before any AI feature goes live, so that no PII reaches the Claude API. | E79: 1. PASS: ZDR agreement with Anthropic is secured and documented; Anthony confirms ZDR status in writing before any EP-16 story moves to In Progress. [PA-73 OPEN: Anthony must confirm whether ZDR is already secured or still pending. If pending, contact api@anthropic.com immediately -- 1 to 3 business day setup window applies.] 2. PASS: DataSanitizer is implemented and enforced on all Claude API calls; no API call is made without DataSanitizer running first. 3. PASS: DataSanitizer applies the confirmed replacement rules exactly: client names replaced with Client A; company names replaced with Corporate Client; contact numbers and emails removed entirely; financial amounts formatted only (no replacement); supplier names replaced with Supplier X - Production (or relevant category label). 4. PASS: AIAuditLog table is present in the trust-ops schema (ops_ai_audit_logs per the database schema map) and receives an entry for every Claude API call made by any AI feature. 5. PASS: Human approval gate is implemented as a reusable component: no AI recommendation from any EP-16 story or EP-12-S06 can be acted upon without explicit PMCM Admin confirmation; the gate cannot be bypassed. 6. PASS: ZDR confirmation is verifiable by inspection: a documented record exists confirming the agreement is in place before the first AI feature goes to production. 7. PASS: DataSanitizer is tested: a unit test confirms that each replacement rule fires correctly on a sample payload containing each PII type. 8. FAIL trigger: Any Claude API call is made without DataSanitizer running, any PII type reaches the API in unsanitized form, AIAuditLog entry is absent for any API call, human approval gate is bypassable, or ZDR agreement is not documented before any EP-16 story moves to In Progress. | F79: Must | G79: D (Anthony) | H79: To Do | I79: None | J79: FR-AI-ZDR; MANDATORY gate for ALL EP-16 stories and EP-12-S06. PA-73 OPEN -- Anthony must confirm ZDR status immediately. ZDR requires Anthropic BAA -- contact api@anthropic.com; 1 to 3 business day setup. CADENCE-DISPLACED: assigned C1, still To Do. CRITICAL: all AI stories blocked until this is Done. | K79: =IF(H79="Done",1,IF(H79="In Progress",0.5,IF(H79="In Review",0.75,0))) -> 0
A80: EP-16 -- AI and Agentic Layer
A81: EP-16 | B81: AI and Agentic Layer | C81: EP-16-S01 | D81: As a PMCM Admin, I want an AI agent to automatically analyze new inquiries before I open them, so that I have a prospect score and event type prediction ready when I review. | E81: 1. PASS: AI inquiry analysis runs automatically within 30 seconds of a new inquiry submission; no PMCM Admin action is required to trigger the analysis. 2. PASS: Analysis is handled by the Haiku model within ai-governance; DataSanitizer runs on all inquiry data before the API call. 3. PASS: Analysis output contains exactly: prospect score (High, Medium, or Low), likely event type prediction, date conflict check result, client fit assessment, and one-sentence recommendation. 4. PASS: ZDR is confirmed active (EP-15-S05 Done) before this feature is deployed. 5. PASS: Analysis output is presented to PMCM Admin as an assistive summary only; PMCM Admin makes all Accept, Pend, and Decline decisions independently without any system pressure or default action based on AI output. 6. PASS: Human approval gate is present: no action is taken on an inquiry based on AI output without explicit PMCM Admin decision. 7. PASS: Every analysis run produces an AIAuditLog entry recording: inquiry ID, timestamp, sanitized input summary, and analysis output. 8. PASS: Analysis output is visible to PMCM Admin only; client, supplier, coordinator, and guest actors cannot access AI analysis results. 9. FAIL trigger: Analysis runs without DataSanitizer, PII reaches the Claude API, AIAuditLog entry is absent, human approval gate is absent or bypassable, AI output implies a system recommendation that replaces PMCM Admin judgment, or analysis output is accessible to non-PMCM actors. | F81: Should | G81: D (Anthony) | H81: To Do | I81: EP-15-S05 | J81: FR-AI-01; Haiku model; Agentic scope; runs within 30 seconds of inquiry submission. Phase 2 scope. BLOCKED until EP-15-S05 Done. | K81: =IF(H81="Done",1,IF(H81="In Progress",0.5,IF(H81="In Review",0.75,0))) -> 0
A82: EP-16 | B82: AI and Agentic Layer | C82: EP-16-S02 | D82: As a PMCM Admin, I want an AI-generated first draft of the event proposal after the CE Builder is populated, so that I can review and finalize rather than write from scratch. | E82: 1. PASS: AI proposal draft is generated after the CE Builder is populated and EP-03-S02 (manual proposal workflow) is available; draft generation requires explicit PMCM Admin trigger, not automatic on CE Builder population. 2. PASS: Draft is generated by the Sonnet model within ai-governance; DataSanitizer runs on all event and client data before the API call. 3. PASS: Draft proposal contains exactly five sections: Executive Summary, Event Concept, Service Package Summary, Investment Summary, and Payment Schedule. 4. PASS: ZDR is confirmed active before this feature is deployed. 5. PASS: Draft is presented to PMCM Admin as an assistive starting point only; PMCM Admin reviews and edits the draft before it becomes a finalized proposal. 6. PASS: Human approval gate is present: draft cannot be sent to the client without explicit PMCM Admin review and send action; no automated send occurs. 7. PASS: Every draft generation run produces an AIAuditLog entry recording: event ID, timestamp, sanitized input summary, and draft generation confirmation. 8. PASS: Draft proposal content is accessible to PMCM Admin only during drafting; client does not see the draft until PMCM Admin explicitly sends the finalized proposal. 9. FAIL trigger: Draft is sent to client without explicit PMCM Admin send action, DataSanitizer is bypassed, AIAuditLog entry is absent, draft contains PII in unsanitized form, or draft is accessible to non-PMCM actors before send. | F82: Should | G82: D (Anthony) | H82: To Do | I82: EP-15-S05, EP-03-S02 | J82: FR-AI-03; Sonnet model; Phase 2 scope. Five proposal sections. Manual proposal workflow (EP-03-S02) is prerequisite. BLOCKED until EP-15-S05 Done. | K82: =IF(H82="Done",1,IF(H82="In Progress",0.5,IF(H82="In Review",0.75,0))) -> 0
A83: EP-16 | B83: AI and Agentic Layer | C83: EP-16-S03 | D83: As a PMCM Admin, I want AI-generated theme and moodboard suggestions based on event type and client preferences, so that I have creative starting points without manual research. | E83: 1. PASS: Theme and moodboard suggestions are generated by explicit PMCM Admin trigger during Bid Workspace or Phase 2 styling production; suggestions do not generate automatically. 2. PASS: Suggestions are generated by the Sonnet model within ai-governance; DataSanitizer runs on all client preference and event type data before the API call. 3. PASS: Output contains exactly two to three concept suggestions; each suggestion includes: concept name, color palette, moodboard description, and reference image search terms. No images are generated; output is text and search terms only. 4. PASS: ZDR is confirmed active before this feature is deployed. 5. PASS: Suggestions are presented to PMCM Admin as assistive creative starting points only; PMCM Admin decides which concept (if any) to pursue independently. 6. PASS: Human approval gate is present: no concept is applied to the event record without explicit PMCM Admin action. 7. PASS: Every suggestion generation run produces an AIAuditLog entry recording: event ID, timestamp, sanitized input summary, and output confirmation. 8. PASS: Suggestion output is accessible to PMCM Admin only; client does not see AI-generated suggestions unless PMCM Admin explicitly shares them. 9. FAIL trigger: Output includes generated images, output contains more or fewer than two to three concepts, DataSanitizer is bypassed, AIAuditLog entry is absent, or suggestions are automatically applied to the event record without PMCM Admin action. | F83: Could | G83: D (Anthony) | H83: To Do | I83: EP-15-S05 | J83: FR-11, FR-15; Sonnet model; Phase 2 scope. Not image generation -- text and search terms only. BLOCKED until EP-15-S05 Done. | K83: =IF(H83="Done",1,IF(H83="In Progress",0.5,IF(H83="In Review",0.75,0))) -> 0
A84: EP-16 | B84: AI and Agentic Layer | C84: EP-16-S04 | D84: As a PMCM Admin, I want a caged Claude chatbot embedded in my dashboard so that I can ask natural language questions about any active event. | E84: 1. PASS: POA Chatbot is embedded in the PMCM Admin dashboard in apps/event; accessible without navigating away from the dashboard. 2. PASS: Chatbot is powered by the Sonnet model within ai-governance; DataSanitizer runs on all event data included in any chatbot prompt before the API call. 3. PASS: Chatbot is caged: it can only access data within PRISM for the queried event; no external data sources are queried and no data leaves PRISM. 4. PASS: ZDR is confirmed active before this feature is deployed. 5. PASS: Chatbot functions as an assistive query tool only; it cannot take any action (update records, send messages, trigger workflows) without explicit PMCM Admin confirmation of each proposed action. 6. PASS: Human approval gate is present and enforced for every draft: PMCM Admin must review, optionally edit, and explicitly send each message; no automated send occurs. 7. PASS: Every chatbot session produces an AIAuditLog entry recording: session timestamp, event context, sanitized query summary, and response summary. 8. PASS: Chatbot is accessible to PMCM Admin only; client, supplier, coordinator, and guest actors cannot access or interact with the chatbot. 9. FAIL trigger: Chatbot queries external data sources, chatbot takes any action without explicit PMCM Admin confirmation, DataSanitizer is bypassed on any prompt, AIAuditLog entry is absent for any session, or chatbot is accessible to non-PMCM actors. | F84: Should | G84: D (Anthony) | H84: To Do | I84: EP-15-S05 | J84: FR-AI-05; Sonnet model; POA Chatbot; caged with ZDR -- no data leaves PRISM. BLOCKED until EP-15-S05 Done. | K84: =IF(H84="Done",1,IF(H84="In Progress",0.5,IF(H84="In Review",0.75,0))) -> 0
A85: EP-16 | B85: AI and Agentic Layer | C85: EP-16-S05 | D85: As a PMCM Admin, I want a probabilistic supplier reliability score shown on each supplier profile, so that I can compare suppliers objectively before selection. | E85: 1. PASS: Supplier reliability score is displayed on each supplier profile visible to PMCM Admin; score is computed using Bayesian math within the backend, not via a Claude API call. 2. PASS: Score is displayed with a confidence band: example format is 87% plus or minus 8%, based on N events where N is the number of reviewed events for that supplier. 3. PASS: Score is computed from: on-time arrival history, complaint rates, quote response times, and contract mismatch frequency; no other inputs are used. 4. PASS: Score requires a minimum number of reviewed events before it displays; below the minimum, the profile shows Insufficient Data rather than a potentially misleading score. [Minimum event count not specified; Anthony must confirm threshold value before AC is finalized.] 5. PASS: Score is visible to PMCM Admin only; not shown to supplier, client, coordinator, or guest actors. 6. PASS: PA-56 resolution required before Done: Anthony must confirm whether DataSanitizer, ZDR confirmation check, and AIAuditLog entry are required for the Bayesian calculation given it does not call the Claude API. Recommendation: yes for governance consistency. 7. FAIL trigger: Score is displayed to non-PMCM actors, score is computed from inputs other than the four confirmed factors, confidence band is absent, or PA-56 is unresolved at Done call. | F85: Could | G85: D (Anthony) | H85: To Do | I85: EP-15-S05, EP-07-S07 | J85: FR-AI-06; Bayesian math only -- no Claude API call. PA-56 OPEN on whether DataSanitizer, ZDR, and AIAuditLog apply. Recommendation: yes for governance consistency. Minimum event threshold count also unconfirmed. | K85: =IF(H85="Done",1,IF(H85="In Progress",0.5,IF(H85="In Review",0.75,0))) -> 0
A86: EP-16 | B86: AI and Agentic Layer | C86: EP-16-S06 | D86: As a PMCM Admin, I want an AI-generated post-event intelligence report analyzing the complete event record, so that learnings are captured without manual report writing. | E86: 1. PASS: AI post-event intelligence report (PEIL) is generated by explicit PMCM Admin trigger after the event is archived (EP-14-S01 Done); report does not generate automatically on archive. 2. PASS: Report is generated by the Sonnet model within ai-governance; DataSanitizer runs on all event record data before the API call. 3. PASS: Report contains exactly three sections: What Worked, What Failed and Why, and Recommended Actions. 4. PASS: ZDR is confirmed active before this feature is deployed. 5. PASS: Report is presented to PMCM Admin as an assistive analytical output; PMCM Admin reviews and interprets the report independently. 6. PASS: Human approval gate is present: if the report includes any recommended action that could affect a supplier record or future event, explicit PMCM Admin confirmation is required before that action is taken. 7. PASS: Report generation produces an AIAuditLog entry recording: event ID, timestamp, sanitized input summary, and report generation confirmation. 8. PASS: PEIL report upgrades the Event Insights Card (New-P2) from EP-14-S01; the deterministic card data from EP-14-S01 remains as a baseline; PEIL adds the AI-generated analytical layer on top. 9. PASS: Report is accessible to PMCM Admin only; client can view a summary if PMCM Admin explicitly shares it; supplier, coordinator, and guest actors cannot access the report. 10. FAIL trigger: Report generates automatically without PMCM Admin trigger, DataSanitizer is bypassed, AIAuditLog entry is absent, report contains PII in unsanitized form, or report is accessible to non-PMCM actors without explicit share action. | F86: Should | G86: D (Anthony) | H86: To Do | I86: EP-15-S05, EP-14-S01 | J86: FR-AI-08; Sonnet model; PEIL; Phase 2 scope. Three sections. Upgrades Event Insights Card from EP-14-S01 deterministic baseline. BLOCKED until EP-15-S05 Done. | K86: =IF(H86="Done",1,IF(H86="In Progress",0.5,IF(H86="In Review",0.75,0))) -> 0
A87: EP-16 | B87: AI and Agentic Layer | C87: EP-16-S07 | D87: As a PMCM Admin, I want AI-generated draft messages at key workflow trigger points, so that I can follow up with clients promptly without writing every message from scratch. | E87: 1. PASS: Draft messages are generated at exactly four trigger points: (a) unsigned conforme after 5 days, (b) unanswered proposal after 3 days, (c) balance payment due in 48 hours, (d) floor plan approval pending after 2 days. 2. PASS: Draft messages are generated by the Haiku model within ai-governance; DataSanitizer runs on all client and event data before each API call. 3. PASS: ZDR is confirmed active before this feature is deployed. 4. PASS: Each draft message is presented to PMCM Admin as an assistive starting point for review and editing; no message is sent automatically under any trigger condition. 5. PASS: Human approval gate is present and enforced for every draft: PMCM Admin must review, optionally edit, and explicitly send each message; no automated send occurs. 6. PASS: Every draft generation run produces an AIAuditLog entry recording: trigger type, event ID, timestamp, sanitized client and event data summary, and draft generation confirmation. 7. PASS: Draft messages surface as a dedicated Drafts tray inside the Command Inbox (EP-02-S01); each draft card is visually distinct from regular alerts and clearly labeled as an AI draft pending review. 8. PASS: Francis (Owner B) has confirmed dashboard UI placement before Anthony calls In Review; this coordination must occur at C4 start. 9. PASS: Draft messages are accessible to PMCM Admin only; no draft is visible to the client until PMCM Admin explicitly sends it. 10. FAIL trigger: Any message is sent automatically without PMCM Admin review and send action, DataSanitizer is bypassed on any trigger, AIAuditLog entry is absent for any draft generation, draft is accessible to non-PMCM actors before send, or Anthony calls In Review without Francis confirming UI placement. | F87: Should | G87: D (Anthony) | H87: To Do | I87: EP-15-S05 | J87: FR-AI-09; Haiku model; Phase 2 scope. UI placement confirmed: Drafts tray inside Command Inbox (EP-02-S01). Visual distinction, three-action review panel, and assistive labeling are non-negotiable. ACTION: Francis to confirm UI placement with Anthony at C4 start. BLOCKED until EP-15-S05 Done. | K87: =IF(H87="Done",1,IF(H87="In Progress",0.5,IF(H87="In Review",0.75,0))) -> 0
A88: EP-17 -- Platform and Backend Architecture
A89: EP-17 | B89: Platform and Backend Architecture | C89: EP-17-S01 | D89: As a platform maintainer, I want the full NestJS backend converted to dependency injection with all phases 1 to 12 verified, so that the modular monolith architecture is clean and testable. | E89: 1. PASS: All 26 services confirmed converted to NestJS DI in Phase 1 child plan (File 34); verification passed with no route or contract changes. 2. PASS: Phases 2 and 3 infrastructure modules (event-core, notification-ops, trust-ops, access-control) extracted and verified; event-ops becomes route compatibility facade. 3. PASS: Phases 4 to 12 extraction plans (Files 46 to 52) all confirmed with evidence-cleared checkboxes; supplier-ops, finance-ops, file-ops, inquiry-onboarding, commercial-ops, compliance-ops, floorplan modules extracted. 4. PASS: All confirmed modules (event-core, notification-ops, trust-ops, access-control, identity-ops, inquiry-onboarding, commercial-ops, compliance-ops, floorplan, file-ops, finance-ops, supplier-ops, staffing-ops, live-ops, closure-ops, ai-governance, event-read-models) pass boundary scan with no reverse import violations. 5. PASS: test:event-ops baseline is 85 tests as of File 52; no unexplained regression below this count. 6. PASS: Phase 13 controller migration confirmed in master plan (File 54). 7. FAIL trigger: Any confirmed module has unexplained test regression below File 52 baseline, boundary scan reveals reverse import violations, or Phase 13 migration is incomplete. | F89: Must | G89: D (Anthony) | H89: Done | I89: None | J89: Files 34-52; NestJS modular monolith Phases 1-13 confirmed complete with verification evidence. Phase 14 (event-ops retirement) and guest-ops (Phase 9) are EP-17-S02 and EP-17-S03 scope. | K89: =IF(H89="Done",1,IF(H89="In Progress",0.5,IF(H89="In Review",0.75,0))) -> 1
A90: EP-17 | B90: Platform and Backend Architecture | C90: EP-17-S02 | D90: As a platform maintainer, I want event-ops fully retired and sample-compatibility module in place, so that the compatibility facade is cleanly removed from the codebase. | E90: 1. PASS: SampleCompatibilityModule is created and imports all 19 required capability modules; circular dependency audit passes with no cycles introduced. 2. PASS: SampleController, SampleCompatibilityService, and SampleStateService are moved to sample-compatibility module and verified by terminal output. 3. PASS: AppModule imports SampleCompatibilityModule; import is verified by terminal output. 4. PASS: event-ops folder is deleted or reduced to index-only; no active service or controller files remain in event-ops after retirement. 5. PASS: packages/api-client/src/event-ops-client.ts rename decision is documented and implemented (PA-131 resolved). 6. PASS: test:event-ops suite passes after retirement; no regression introduced. 7. PASS: All four File 55 unchecked task checkboxes are completed with terminal output evidence; master plan checkbox is not sufficient. 8. PASS: Verification evidence table is present with terminal output for all tasks. 9. FAIL trigger: Any event-ops directory files remain without documented rationale, verification evidence table is absent, circular dependency is introduced by SampleCompatibilityModule imports, or test suite regresses after retirement. | F90: Must | G90: D (Anthony) | H90: Blocked | I90: EP-17-S01 | J90: BLOCKED: File 55 child plan task checkboxes unchecked, no verification evidence table. Master plan checkbox NOT authoritative. FIRST ACTION at C3 start: Anthony runs all four File 55 verification commands, pastes terminal output as evidence. Resolves PA-92, PA-95, PA-127, PA-128, PA-129, PA-130, PA-131. | K90: =IF(H90="Done",1,IF(H90="In Progress",0.5,IF(H90="In Review",0.75,0))) -> 0
A91: EP-17 | B91: Platform and Backend Architecture | C91: EP-17-S03 | D91: As a platform maintainer, I want guest-ops module fully implemented and verified, so that guest workflow commands and read models are properly encapsulated. | E91: 1. PASS: GuestWorkflowService is implemented inside the guest-ops module and verified by terminal output evidence. 2. PASS: GUEST_COMMANDS and GUEST_READER port tokens are bound with concrete implementations; no unbound token errors on module load. 3. PASS: EventReadModelsService is injected with GUEST_READER and the injection is verified; no conflict with Phase 11 read-model extraction timeline (PA-123 must be assessed before Done). 4. PASS: Guest actor cannot read PMCM planning or live payload through any guest-ops route; role boundary enforced and tested. 5. PASS: Privacy consent gate is implemented: guest cannot complete check-in or submit feedback without consenting to data processing terms. 6. PASS: mapGuestEvent function excludes privateNotes and PMCM-only fields from all guest-facing payloads; verified by inspection of output shape. 7. PASS: GuestOpsModule imports FileOpsModule with a documented rationale for the dependency (PA-121 must be resolved before Done). 8. PASS: test:event-ops count is reported after guest-ops implementation; impact on the 85 count baseline is documented (PA-125). 9. PASS: Verification evidence table is present with terminal output for all tasks; master plan checkbox alone is not sufficient. 10. FAIL trigger: Verification evidence table is absent, GUEST_COMMANDS or GUEST_READER tokens are unbound, guest actor can access PMCM planning payload, privacy consent gate is absent, or PA-121 and PA-123 remain unresolved at Done call. | F91: Must | G91: D (Anthony) | H91: Blocked | I91: EP-17-S01 | J91: BLOCKED: File 53 child plan task checkboxes unchecked, no verification evidence table. Master plan (File 54) claims completion; child plan contradicts it. Child plan is authoritative. FIRST ACTION at C3 start: Anthony runs File 53 verification commands, pastes terminal output as evidence. Resolves PA-120 through PA-126. | K91: =IF(H91="Done",1,IF(H91="In Progress",0.5,IF(H91="In Review",0.75,0))) -> 0
A92: EP-18 -- Design System and Shared UI
A93: EP-18 | B93: Design System and Shared UI | C93: EP-18-S01 | D93: As any user, I want a consistent design system applied across all five portals, so that the system feels like one coherent PMCM operating system. | E93: 1. PASS: packages/ui contains the canonical design token set (colors, typography, spacing, breakpoints) used by all five portals (apps/event, apps/client, apps/supplier, apps/guest, apps/api-adjacent surfaces). 2. PASS: All five portals consume design tokens from packages/ui; no app-local copies of token values that duplicate the canonical set remain. 3. PASS: Shared UI components (buttons, inputs, modals, alerts, empty states, loading states) are sourced from packages/ui; app-local copies of components that duplicate shared components are removed. 4. PASS: Visual consistency check: equivalent UI elements (primary button, error state, empty state) render identically across all five portals without per-app style overrides. 5. PASS: Maxine route-review log includes at minimum one entry per portal confirming design token application (P1 missing task from File 33). 6. PASS: No regression is introduced in any portal existing functionality by the design token consolidation; all existing routes render correctly after token migration. 7. FAIL trigger: Any portal retains app-local token copies that duplicate packages/ui values, equivalent UI elements render inconsistently across portals, or route-review log entries are absent for any portal. | F93: Must | G93: A (Maxine) | H93: In Progress | I93: None | J93: FL-016; packages/ui, design tokens, shared shell patterns; confirmed Partial per File 9. Shared UI/tokens exist; app-local UI copies remain. MUST close in first days of C2. Maxine C2 first priority. | K93: =IF(H93="Done",1,IF(H93="In Progress",0.5,IF(H93="In Review",0.75,0))) -> 0.5
A94: EP-18 | B94: Design System and Shared UI | C94: EP-18-S02 | D94: As a developer, I want a shared route inventory and navigation shell, so that cross-portal navigation is consistent and traceable. | E94: 1. PASS: A shared route inventory document exists and lists every confirmed route across all five portals with: route path, owning portal, owning owner, and current redesign severity (S0-S3/Gate per File 14 taxonomy). 2. PASS: Navigation shell is implemented in packages/ui and consumed by all five portals; no portal implements its own independent navigation shell that duplicates shared shell behavior. 3. PASS: Cross-portal navigation (where applicable) routes correctly between portals without exposing unauthorized routes to wrong role actors. 4. PASS: Route inventory is updated before any route-level merge per DoD candidate L. 5. PASS: Maxine route-review log is initiated and contains at minimum one entry confirming the shell foundation is applied per portal. 6. PASS: Navigation shell renders correctly on mobile and desktop breakpoints for all five portals. 7. FAIL trigger: Any portal implements an independent navigation shell that duplicates shared shell behavior, route inventory is missing entries for any confirmed portal route, or cross-portal navigation routes a user to an unauthorized surface. | F94: Must | G94: A (Maxine) | H94: To Do | I94: EP-18-S01 | J94: Route inventory; shell foundation; Maxine route-review log required before July closeout (P1 missing task from File 33). | K94: =IF(H94="Done",1,IF(H94="In Progress",0.5,IF(H94="In Review",0.75,0))) -> 0

Sheet Dashboard
A1: P.R.I.S.M. AC TRACKER -- SYSTEM DASHBOARD
A2: Overall System Completion %
A3: =(COUNTIF(Tracker!H:H,"Done")*100+COUNTIF(Tracker!H:H,"In Progress")*50+COUNTIF(Tracker!H:H,"In Review")*75)/MAX(1,COUNTIF(Tracker!C:C,"EP-*")) -> 28.333333
A5: Completion by Cadence
A6: C1 | B6: C2 | C6: C3 | D6: C4
A7: =(COUNTIFS(#REF!,"C1",Tracker!H:H,"Done")*100+COUNTIFS(#REF!,"C1",Tracker!H:H,"In Progress")*50+COUNTIFS(#REF!,"C1",Tracker!H:H,"In Review")*75)/MAX(1,COUNTIF(#REF!,"C1")) -> #VALUE! | B7: =(COUNTIFS(#REF!,"C2",Tracker!H:H,"Done")*100+COUNTIFS(#REF!,"C2",Tracker!H:H,"In Progress")*50+COUNTIFS(#REF!,"C2",Tracker!H:H,"In Review")*75)/MAX(1,COUNTIF(#REF!,"C2")) -> #VALUE! | C7: =(COUNTIFS(#REF!,"C3",Tracker!H:H,"Done")*100+COUNTIFS(#REF!,"C3",Tracker!H:H,"In Progress")*50+COUNTIFS(#REF!,"C3",Tracker!H:H,"In Review")*75)/MAX(1,COUNTIF(#REF!,"C3")) -> #VALUE! | D7: =(COUNTIFS(#REF!,"C4",Tracker!H:H,"Done")*100+COUNTIFS(#REF!,"C4",Tracker!H:H,"In Progress")*50+COUNTIFS(#REF!,"C4",Tracker!H:H,"In Review")*75)/MAX(1,COUNTIF(#REF!,"C4")) -> #VALUE!
A9: Stories by Status
A10: Done | B10: In Progress | C10: In Review | D10: To Do | E10: Blocked
A11: =COUNTIF(Tracker!H:H,"Done") -> 17 | B11: =COUNTIF(Tracker!H:H,"In Progress") -> 7 | C11: =COUNTIF(Tracker!H:H,"In Review") -> 1 | D11: =COUNTIF(Tracker!H:H,"To Do") -> 46 | E11: =COUNTIF(Tracker!H:H,"Blocked") -> 4
A13: Completion by Owner -- Done / In Progress / Total and Weighted %
A14: Owner | B14: Person | C14: Done | D14: In Progress | E14: Total Stories | F14: Completion %
A15: A (Maxine) | B15: Maxine | C15: =COUNTIFS(Tracker!G:G,"A (Maxine)",Tracker!H:H,"Done") -> 0 | D15: =COUNTIFS(Tracker!G:G,"A (Maxine)",Tracker!H:H,"In Progress") -> 1 | E15: =COUNTIF(Tracker!G:G,"A (Maxine)") & " stories" -> 2 stories | F15: =(COUNTIFS(Tracker!G:G,"A (Maxine)",Tracker!H:H,"Done")*100+COUNTIFS(Tracker!G:G,"A (Maxine)",Tracker!H:H,"In Progress")*50)/MAX(1,COUNTIF(Tracker!G:G,"A (Maxine)")) -> 25
A16: B (Francis) | B16: Francis | C16: =COUNTIFS(Tracker!G:G,"B (Francis)",Tracker!H:H,"Done") -> 9 | D16: =COUNTIFS(Tracker!G:G,"B (Francis)",Tracker!H:H,"In Progress") -> 4 | E16: =COUNTIF(Tracker!G:G,"B (Francis)") & " stories" -> 36 stories | F16: =(COUNTIFS(Tracker!G:G,"B (Francis)",Tracker!H:H,"Done")*100+COUNTIFS(Tracker!G:G,"B (Francis)",Tracker!H:H,"In Progress")*50)/MAX(1,COUNTIF(Tracker!G:G,"B (Francis)")) -> 30.555556
A17: C (Ethan) | B17: Ethan | C17: =COUNTIFS(Tracker!G:G,"C (Ethan)",Tracker!H:H,"Done") -> 4 | D17: =COUNTIFS(Tracker!G:G,"C (Ethan)",Tracker!H:H,"In Progress") -> 2 | E17: =COUNTIF(Tracker!G:G,"C (Ethan)") & " stories" -> 16 stories | F17: =(COUNTIFS(Tracker!G:G,"C (Ethan)",Tracker!H:H,"Done")*100+COUNTIFS(Tracker!G:G,"C (Ethan)",Tracker!H:H,"In Progress")*50)/MAX(1,COUNTIF(Tracker!G:G,"C (Ethan)")) -> 31.25
A18: D (Anthony) | B18: Anthony | C18: =COUNTIFS(Tracker!G:G,"D (Anthony)",Tracker!H:H,"Done") -> 4 | D18: =COUNTIFS(Tracker!G:G,"D (Anthony)",Tracker!H:H,"In Progress") -> 0 | E18: =COUNTIF(Tracker!G:G,"D (Anthony)") & " stories" -> 21 stories | F18: =(COUNTIFS(Tracker!G:G,"D (Anthony)",Tracker!H:H,"Done")*100+COUNTIFS(Tracker!G:G,"D (Anthony)",Tracker!H:H,"In Progress")*50)/MAX(1,COUNTIF(Tracker!G:G,"D (Anthony)")) -> 19.047619
A20: Stories by MoSCoW Priority -- Count and Completion
A21: Priority | B21: Total Stories | C21: Done | D21: In Progress | E21: Completion %
A22: Must | B22: =COUNTIF(Tracker!F:F,"Must") -> 51 | C22: =COUNTIFS(Tracker!F:F,"Must",Tracker!H:H,"Done") -> 15 | D22: =COUNTIFS(Tracker!F:F,"Must",Tracker!H:H,"In Progress") -> 7 | E22: =(COUNTIFS(Tracker!F:F,"Must",Tracker!H:H,"Done")*100+COUNTIFS(Tracker!F:F,"Must",Tracker!H:H,"In Progress")*50)/MAX(1,COUNTIF(Tracker!F:F,"Must")) -> 36.27451
A23: Should | B23: =COUNTIF(Tracker!F:F,"Should") -> 18 | C23: =COUNTIFS(Tracker!F:F,"Should",Tracker!H:H,"Done") -> 1 | D23: =COUNTIFS(Tracker!F:F,"Should",Tracker!H:H,"In Progress") -> 0 | E23: =(COUNTIFS(Tracker!F:F,"Should",Tracker!H:H,"Done")*100+COUNTIFS(Tracker!F:F,"Should",Tracker!H:H,"In Progress")*50)/MAX(1,COUNTIF(Tracker!F:F,"Should")) -> 5.5555556
A24: Could | B24: =COUNTIF(Tracker!F:F,"Could") -> 6 | C24: =COUNTIFS(Tracker!F:F,"Could",Tracker!H:H,"Done") -> 1 | D24: =COUNTIFS(Tracker!F:F,"Could",Tracker!H:H,"In Progress") -> 0 | E24: =(COUNTIFS(Tracker!F:F,"Could",Tracker!H:H,"Done")*100+COUNTIFS(Tracker!F:F,"Could",Tracker!H:H,"In Progress")*50)/MAX(1,COUNTIF(Tracker!F:F,"Could")) -> 16.666667
A26: Completion % by Epic
A27: Epic ID | B27: Epic Name | C27: Total Stories | D27: Done | E27: Completion %
A28: EP-01 | B28: Inquiry and Client Onboarding | C28: =COUNTIF(Tracker!A:A,"EP-01") -> 4 | D28: =COUNTIFS(Tracker!A:A,"EP-01",Tracker!H:H,"Done") -> 4 | E28: =(COUNTIFS(Tracker!A:A,"EP-01",Tracker!H:H,"Done")*100+COUNTIFS(Tracker!A:A,"EP-01",Tracker!H:H,"In Progress")*50+COUNTIFS(Tracker!A:A,"EP-01",Tracker!H:H,"In Review")*75)/MAX(1,COUNTIF(Tracker!A:A,"EP-01")) -> 100
A29: EP-02 | B29: PMCM Command and Coordination | C29: =COUNTIF(Tracker!A:A,"EP-02") -> 5 | D29: =COUNTIFS(Tracker!A:A,"EP-02",Tracker!H:H,"Done") -> 4 | E29: =(COUNTIFS(Tracker!A:A,"EP-02",Tracker!H:H,"Done")*100+COUNTIFS(Tracker!A:A,"EP-02",Tracker!H:H,"In Progress")*50+COUNTIFS(Tracker!A:A,"EP-02",Tracker!H:H,"In Review")*75)/MAX(1,COUNTIF(Tracker!A:A,"EP-02")) -> 90
A30: EP-03 | B30: Briefing and Proposal | C30: =COUNTIF(Tracker!A:A,"EP-03") -> 2 | D30: =COUNTIFS(Tracker!A:A,"EP-03",Tracker!H:H,"Done") -> 0 | E30: =(COUNTIFS(Tracker!A:A,"EP-03",Tracker!H:H,"Done")*100+COUNTIFS(Tracker!A:A,"EP-03",Tracker!H:H,"In Progress")*50+COUNTIFS(Tracker!A:A,"EP-03",Tracker!H:H,"In Review")*75)/MAX(1,COUNTIF(Tracker!A:A,"EP-03")) -> 0
A31: EP-04 | B31: Contract and Conforme | C31: =COUNTIF(Tracker!A:A,"EP-04") -> 2 | D31: =COUNTIFS(Tracker!A:A,"EP-04",Tracker!H:H,"Done") -> 0 | E31: =(COUNTIFS(Tracker!A:A,"EP-04",Tracker!H:H,"Done")*100+COUNTIFS(Tracker!A:A,"EP-04",Tracker!H:H,"In Progress")*50+COUNTIFS(Tracker!A:A,"EP-04",Tracker!H:H,"In Review")*75)/MAX(1,COUNTIF(Tracker!A:A,"EP-04")) -> 25
A32: EP-05 | B32: Floor Plan and Venue | C32: =COUNTIF(Tracker!A:A,"EP-05") -> 4 | D32: =COUNTIFS(Tracker!A:A,"EP-05",Tracker!H:H,"Done") -> 0 | E32: =(COUNTIFS(Tracker!A:A,"EP-05",Tracker!H:H,"Done")*100+COUNTIFS(Tracker!A:A,"EP-05",Tracker!H:H,"In Progress")*50+COUNTIFS(Tracker!A:A,"EP-05",Tracker!H:H,"In Review")*75)/MAX(1,COUNTIF(Tracker!A:A,"EP-05")) -> 18.75
A33: EP-06 | B33: Compliance and Change Enablement | C33: =COUNTIF(Tracker!A:A,"EP-06") -> 3 | D33: =COUNTIFS(Tracker!A:A,"EP-06",Tracker!H:H,"Done") -> 0 | E33: =(COUNTIFS(Tracker!A:A,"EP-06",Tracker!H:H,"Done")*100+COUNTIFS(Tracker!A:A,"EP-06",Tracker!H:H,"In Progress")*50+COUNTIFS(Tracker!A:A,"EP-06",Tracker!H:H,"In Review")*75)/MAX(1,COUNTIF(Tracker!A:A,"EP-06")) -> 0
A34: EP-07 | B34: Supplier Network and Readiness | C34: =COUNTIF(Tracker!A:A,"EP-07") -> 10 | D34: =COUNTIFS(Tracker!A:A,"EP-07",Tracker!H:H,"Done") -> 5 | E34: =(COUNTIFS(Tracker!A:A,"EP-07",Tracker!H:H,"Done")*100+COUNTIFS(Tracker!A:A,"EP-07",Tracker!H:H,"In Progress")*50+COUNTIFS(Tracker!A:A,"EP-07",Tracker!H:H,"In Review")*75)/MAX(1,COUNTIF(Tracker!A:A,"EP-07")) -> 50
A35: EP-08 | B35: Finance and Billing | C35: =COUNTIF(Tracker!A:A,"EP-08") -> 3 | D35: =COUNTIFS(Tracker!A:A,"EP-08",Tracker!H:H,"Done") -> 0 | E35: =(COUNTIFS(Tracker!A:A,"EP-08",Tracker!H:H,"Done")*100+COUNTIFS(Tracker!A:A,"EP-08",Tracker!H:H,"In Progress")*50+COUNTIFS(Tracker!A:A,"EP-08",Tracker!H:H,"In Review")*75)/MAX(1,COUNTIF(Tracker!A:A,"EP-08")) -> 0
A36: EP-09 | B36: File and Document Management | C36: =COUNTIF(Tracker!A:A,"EP-09") -> 2 | D36: =COUNTIFS(Tracker!A:A,"EP-09",Tracker!H:H,"Done") -> 0 | E36: =(COUNTIFS(Tracker!A:A,"EP-09",Tracker!H:H,"Done")*100+COUNTIFS(Tracker!A:A,"EP-09",Tracker!H:H,"In Progress")*50+COUNTIFS(Tracker!A:A,"EP-09",Tracker!H:H,"In Review")*75)/MAX(1,COUNTIF(Tracker!A:A,"EP-09")) -> 0
A37: EP-10 | B37: Client Portal | C37: =COUNTIF(Tracker!A:A,"EP-10") -> 3 | D37: =COUNTIFS(Tracker!A:A,"EP-10",Tracker!H:H,"Done") -> 0 | E37: =(COUNTIFS(Tracker!A:A,"EP-10",Tracker!H:H,"Done")*100+COUNTIFS(Tracker!A:A,"EP-10",Tracker!H:H,"In Progress")*50+COUNTIFS(Tracker!A:A,"EP-10",Tracker!H:H,"In Review")*75)/MAX(1,COUNTIF(Tracker!A:A,"EP-10")) -> 16.666667
A38: EP-11 | B38: Coordinator Experience and Live Ops | C38: =COUNTIF(Tracker!A:A,"EP-11") -> 5 | D38: =COUNTIFS(Tracker!A:A,"EP-11",Tracker!H:H,"Done") -> 0 | E38: =(COUNTIFS(Tracker!A:A,"EP-11",Tracker!H:H,"Done")*100+COUNTIFS(Tracker!A:A,"EP-11",Tracker!H:H,"In Progress")*50+COUNTIFS(Tracker!A:A,"EP-11",Tracker!H:H,"In Review")*75)/MAX(1,COUNTIF(Tracker!A:A,"EP-11")) -> 0
A39: EP-12 | B39: Event Day Operations | C39: =COUNTIF(Tracker!A:A,"EP-12") -> 6 | D39: =COUNTIFS(Tracker!A:A,"EP-12",Tracker!H:H,"Done") -> 1 | E39: =(COUNTIFS(Tracker!A:A,"EP-12",Tracker!H:H,"Done")*100+COUNTIFS(Tracker!A:A,"EP-12",Tracker!H:H,"In Progress")*50+COUNTIFS(Tracker!A:A,"EP-12",Tracker!H:H,"In Review")*75)/MAX(1,COUNTIF(Tracker!A:A,"EP-12")) -> 25
A40: EP-13 | B40: Guest Experience and Digital Registration | C40: =COUNTIF(Tracker!A:A,"EP-13") -> 7 | D40: =COUNTIFS(Tracker!A:A,"EP-13",Tracker!H:H,"Done") -> 0 | E40: =(COUNTIFS(Tracker!A:A,"EP-13",Tracker!H:H,"Done")*100+COUNTIFS(Tracker!A:A,"EP-13",Tracker!H:H,"In Progress")*50+COUNTIFS(Tracker!A:A,"EP-13",Tracker!H:H,"In Review")*75)/MAX(1,COUNTIF(Tracker!A:A,"EP-13")) -> 7.1428571
A41: EP-14 | B41: Closure and Archive | C41: =COUNTIF(Tracker!A:A,"EP-14") -> 2 | D41: =COUNTIFS(Tracker!A:A,"EP-14",Tracker!H:H,"Done") -> 0 | E41: =(COUNTIFS(Tracker!A:A,"EP-14",Tracker!H:H,"Done")*100+COUNTIFS(Tracker!A:A,"EP-14",Tracker!H:H,"In Progress")*50+COUNTIFS(Tracker!A:A,"EP-14",Tracker!H:H,"In Review")*75)/MAX(1,COUNTIF(Tracker!A:A,"EP-14")) -> 25
A42: EP-15 | B42: Security, Privacy, and Auth | C42: =COUNTIF(Tracker!A:A,"EP-15") -> 5 | D42: =COUNTIFS(Tracker!A:A,"EP-15",Tracker!H:H,"Done") -> 2 | E42: =(COUNTIFS(Tracker!A:A,"EP-15",Tracker!H:H,"Done")*100+COUNTIFS(Tracker!A:A,"EP-15",Tracker!H:H,"In Progress")*50+COUNTIFS(Tracker!A:A,"EP-15",Tracker!H:H,"In Review")*75)/MAX(1,COUNTIF(Tracker!A:A,"EP-15")) -> 40
A43: EP-16 | B43: AI and Agentic Layer | C43: =COUNTIF(Tracker!A:A,"EP-16") -> 7 | D43: =COUNTIFS(Tracker!A:A,"EP-16",Tracker!H:H,"Done") -> 0 | E43: =(COUNTIFS(Tracker!A:A,"EP-16",Tracker!H:H,"Done")*100+COUNTIFS(Tracker!A:A,"EP-16",Tracker!H:H,"In Progress")*50+COUNTIFS(Tracker!A:A,"EP-16",Tracker!H:H,"In Review")*75)/MAX(1,COUNTIF(Tracker!A:A,"EP-16")) -> 0
A44: EP-17 | B44: Platform and Backend Architecture | C44: =COUNTIF(Tracker!A:A,"EP-17") -> 3 | D44: =COUNTIFS(Tracker!A:A,"EP-17",Tracker!H:H,"Done") -> 1 | E44: =(COUNTIFS(Tracker!A:A,"EP-17",Tracker!H:H,"Done")*100+COUNTIFS(Tracker!A:A,"EP-17",Tracker!H:H,"In Progress")*50+COUNTIFS(Tracker!A:A,"EP-17",Tracker!H:H,"In Review")*75)/MAX(1,COUNTIF(Tracker!A:A,"EP-17")) -> 33.333333
A45: EP-18 | B45: Design System and Shared UI | C45: =COUNTIF(Tracker!A:A,"EP-18") -> 2 | D45: =COUNTIFS(Tracker!A:A,"EP-18",Tracker!H:H,"Done") -> 0 | E45: =(COUNTIFS(Tracker!A:A,"EP-18",Tracker!H:H,"Done")*100+COUNTIFS(Tracker!A:A,"EP-18",Tracker!H:H,"In Progress")*50+COUNTIFS(Tracker!A:A,"EP-18",Tracker!H:H,"In Review")*75)/MAX(1,COUNTIF(Tracker!A:A,"EP-18")) -> 25

Sheet Legend
A1: P.R.I.S.M. AC Tracker -- Legend and Color Guide
A2: 1. Status -- Definitions, Colors, and Completion % Weight
A3: Color Swatch | B3: Status | C3: Meaning | D3: Completion % | E3: Where Applied
A4: Done | B4: Done | C4: All AC pass, merged to main, reviewed by at least one other owner. | D4: 100% | E4: Tracker, AC Detail
A5: In Progress | B5: In Progress | C5: Actively being built. | D5: 50% | E5: Tracker, AC Detail, Cadence Checklist
A6: In Review | B6: In Review | C6: Built, awaiting review or verification evidence. | D6: 75% | E6: Tracker only
A7: To Do | B7: To Do | C7: Not yet started; unblocked and ready to begin. | D7: 0% | E7: Tracker, AC Detail, Cadence Checklist
A8: Blocked | B8: Blocked | C8: Cannot proceed. Reason and unblock condition in Notes. Not used in Cadence Checklist. | D8: 0% | E8: Tracker, AC Detail
A9: 2. MoSCoW Priority -- Definitions and Colors (text color in Priority column)
A10: Color Swatch | B10: Priority | C10: Meaning | D10: Story Count
A11: Must | B11: Must | C11: Required for July 31 system completion. Failure = incomplete system. | D11: 51 stories
A12: Should | B12: Should | C12: Important but not blocking July 31 if deprioritized with documented reason. | D12: 18 stories
A13: Could | B13: Could | C13: Desirable if capacity exists after Must and Should stories are Done. | D13: 6 stories
A14: Won't | B14: Won't | C14: Explicitly post-July or out of scope for this tracker. | D14: 0 stories
A15: 3. Cadence -- Definitions and Colors (row background tint in Tracker)
A16: Color Swatch | B16: Cadence | C16: Dates | D16: Type | E16: Status
A17: C1 | B17: C1 | C17: June 15-20, 2026 | D17: Baseline / retrospective / Done | E17: CLOSED
A18: C2 | B18: C2 | C18: June 22 - July 3, 2026 | D18: First-slice delivery | E18: ACTIVE NOW
A19: C3 | B19: C3 | C19: July 6-17, 2026 | D19: Workflow completion; feature freeze at close | E19: UPCOMING
A20: C4 | B20: C4 | C20: July 20-31, 2026 | D20: Stabilization and evidence only; hard stop July 31 | E20: UPCOMING
A21: 4. Owners -- Definitions and Story Counts (updated after shared story reassignment)
A22: Owner | B22: Person | C22: Primary Scope | D22: Story Count
A23: A (Maxine) | B23: Maxine | C23: packages/ui, design tokens, route inventory, shared shell patterns | D23: 2 stories
A24: B (Francis) | B24: Francis | C24: apps/event (port 3004), PMCM command, coordinator, event workspace, live ops, closure. Includes EP-06-S01 and EP-13-S05 (previously shared). | D24: 36 stories
A25: C (Ethan) | B25: Ethan | C25: apps/client (port 3001), apps/supplier (port 3002), apps/guest (port 3003), public flows | D25: 16 stories
A26: D (Anthony) | B26: Anthony | C26: apps/api (port 4000), packages/types, packages/api-client, verification, docs. Includes EP-09-S02 and EP-12-S02 (previously shared). | D26: 25 stories
A27: 5. Epic Separator Row -- Dark rows grouping stories by Epic in Tracker
A28: Color Swatch | B28: Element | C28: Description
A29: Epic Row | B29: Epic Separator | C29: Dark navy row dividing each Epic group in the Tracker tab.
A30: 6. PA Resolution Colors -- Used in Cadence Review Guide tab
A31: Color Swatch | B31: Meaning
A32: Sample | B32: Critical or unresolved PA requiring immediate action
A33: Sample | B33: Important notice or feature freeze rule
A34: Sample | B34: Resolved PA
A35: Sample | B35: Standard informational row
A36: 7. How to Use -- Dropdown and Auto Row Coloring
A37: In the Tracker tab and AC Detail tab, click any cell in the Status column (column I in Tracker, column E in AC Detail). A dropdown arrow appears -- select a status and the entire row automatically changes to the matching color above. The Dashboard Overall System Completion % and all breakdown figures update automatically. In the Cadence Checklist tab, the same applies with three options only: Done, In Progress, To Do.

Sheet DoD
A1: P.R.I.S.M. -- Global Definition of Done (14 Criteria)
A2: # | B2: Criterion | C2: Description
A3: 1 | B3: Code merged and builds clean | C3: Code is merged to main branch and builds clean.
A4: 2 | B4: All AC pass | C4: All of the story acceptance criteria pass.
A5: 3 | B5: Reviewed by another owner | C5: The work has been reviewed by at least one other owner.
A6: 4 | B6: Runs without errors | C6: It runs without errors in the shared/runtime environment.
A7: 5 | B7: User-facing states present | C7: User-facing text, states, and error handling are present, not stubbed.
A8: A | B8: Scope regression check | C8: No feature outside story scope was introduced or removed.
A9: B | B9: Build and typecheck pass | C9: Build and typecheck pass clean with zero errors after merge.
A10: C | B10: Role-boundary scan | C10: No unauthorized actor can access data or actions introduced by this story.
A11: E | B11: Empty state handled | C11: Every list, inbox, or dashboard introduced by this story has a confirmed empty state.
A12: F | B12: Loading state handled | C12: Every async data fetch introduced by this story has a confirmed loading state.
A13: G | B13: Error state handled | C13: Every async data fetch has a confirmed error state distinct from empty state.
... A20: Q | B20: State summary gate | C20: Empty, loading, error, no-permission, and high-volume states are all accounted for (consolidates E F G H I).
A22: Notes-Only Gate Conditions (verified alongside C; not standalone DoD rows)
A23: D | B23: Role boundary data access (notes-only) | C23: No actor can access data outside their confirmed role boundary. Verified in same pass as C.
A24: N | B24: Public pages (notes-only) | C24: Public pages do not link directly to dashboards. Applies to public-facing stories only.
A25: O | B25: Client floorplan mutation (notes-only) | C25: Clients cannot mutate official floorplans. Applies to floor plan stories (EP-05).
A26: P | B26: PMCM-only data (notes-only) | C26: PMCM-only data stays PMCM-only. Applies to all stories touching PMCM internal data.

Sheet Cadence Checklist
A1: P.R.I.S.M. AC Tracker -- Cadence Checklist
A2: Team CG | University of Santo Tomas | July 31, 2026 Hard Deadline | Select status from dropdown -- row colors update automatically | Stories weight 2pts, all other items weight 1pt
A4: C1 -- Cadence 1 Retrospective Audit | June 15-20, 2026 | Status: CLOSED
A5: C1 was the baseline and planning cadence. All items below should be Done. Any To Do or In Progress item here is a carry-over risk into C2 and must be resolved before C2 closes.
A6: Type | B6: Item / Description | C6: Owner | D6: Weight | E6: Status | F6: Done Criteria | G6: Notes / Context
A7: STORIES -- Must be Done from C1
A8: Story | B8: EP-01-S01 -- Public inquiry form submission | C8: C (Ethan) | D8: 2 | E8: Done | F8: Form accessible without login, all required fields captured, duplicate detection works, PMCM inbox receives submission.
A9: Story | B9: EP-01-S02 -- Log inquiry on behalf of walk-in or phone client | C9: B (Francis) | D9: 2 | E9: Done | F9: On-behalf function accessible only to PMCM Admin, channel marker present, duplicate detection applies, logging admin identity recorded.
A10: Story | B10: EP-01-S03 -- Client account onboarding after inquiry approval | C10: D (Anthony) | D10: 2 | E10: Done | F10: Onboarding triggers only after inquiry approved, client portal access activates, audit log entry recorded.
A11: Story | B11: EP-01-S04 -- Referral source dropdown with confirmed values | C11: B (Francis) | D11: 2 | E11: Done | F11: Dropdown present on both forms, field required, value saved to inquiry record. Note: sixth value still pending PA-62 -- story is live but AC item 2 placeholder remains.
A12: Story | B12: EP-02-S01 -- PMCM command inbox on dashboard | C12: B (Francis) | D12: 2 | E12: Done | F12: Command inbox accessible from PMCM dashboard, rows sourced from PrismPmcmCommandInbox, critical alerts visually distinct, empty state correct, barrel export resolves without error.
A13: Story | B13: EP-07-S01 -- Supplier directory with category tagging and reliability notes | C13: B (Francis) | D13: 2 | E13: Done | F13: All 8 supplier categories present, aggregate review rating PMCM-only, BNI flag persists, reliability notes stored, non-PMCM actors denied.
A14: Story | B14: EP-07-S02 -- Quote requests to Tier 1 and Tier 2 suppliers | C14: B (Francis) | D14: 2 | E14: Done | F14: Quote request sent per category, one revision limit enforced, quote locked after supplier selected, quote data not exposed to non-PMCM or non-supplier actors.
A15: Story | B15: EP-07-S03 -- Supplier quote confirmation and availability check | C15: C (Ethan) | D15: 2 | E15: Done | F15: Supplier explicitly confirms availability and accepts terms, no raw AI output shown to supplier, supplier can only see own quote requests.
A16: Story | B16: EP-07-S07 -- Internal supplier review after event close | C16: B (Francis) | D16: 2 | E16: Done | F16: Only Ms. Mys and EA can access Internal Supplier Review surface, ratings not visible to supplier or other actors. NOTE: PA-71 still open -- Done call needs retrospective confirmation from Ms. Mys on EA role.
A17: Story | B17: EP-12-S03 -- Supplier withdrawal with mandatory reason | C17: C (Ethan) | D17: 2 | E17: Done | F17: Withdrawal submittable only with reason, requireSupplierAdmin policy enforced, freeze window withdrawal triggers Emergency Change classification.
A18: Story | B18: EP-15-S01 -- Mandatory 2FA via TOTP with lockout and session controls | C18: D (Anthony) | D18: 2 | E18: Done | F18: 2FA mandatory for PMCM Admin via TOTP, lockout after 5 failures for 10 minutes, password reset link expires at 15 minutes. NOTE: PA-69 open -- minimum password requirements still need Ms. Mys confirmation.
A19: Story | B19: EP-15-S02 -- Privacy and PII management layer | C19: D (Anthony) | D19: 2 | E19: Done | F19: Privacy Notice shown on first login to all portals, data export and anonymization functions present, PII Inventory PMCM Admin only. NOTE: PA-72 open -- PII Inventory editability still needs Ms. Mys confirmation.
... A21: Story | B21: EP-18-S01 -- Design system and shared UI across all five portals | C21: A (Maxine) | D21: 2 | E21: In Progress | F21: All five portals consume design tokens from packages/ui, no app-local token copies, shared components sourced from packages/ui, route-review log entries present for all portals.
A22: PA RESOLUTIONS -- Must be confirmed from C1 or carried clearly into C2
A23: PA Resolution | B23: PA-62 -- Confirm sixth referral source dropdown value | C23: Francis + Ms. Mys | D23: 1 | E23: To Do | F23: Ms. Mys names the sixth value in writing or verbally confirmed and recorded. Five confirmed: Facebook, Website, BNI, Walk-In, Log on Behalf. | G23: Blocks AC item 2 finalization in EP-01-S04. Low risk but must close before tracker is considered fully clean.
A24: PA Resolution | B24: PA-69 -- Minimum password requirements confirmed | C24: Anthony + Ms. Mys | D24: 1 | E24: To Do | F24: Anthony and Ms. Mys confirm specific length and complexity values in writing. | G24: Blocks AC item 5 finalization in EP-15-S01. Story is live but AC placeholder remains.
A25: PA Resolution | B25: PA-71 -- EA role full name and login type confirmed | C25: Ms. Mys | D25: 1 | E25: To Do | F25: Ms. Mys confirms EA full role name and whether EA has own system login or is a sub-role under PMCM Admin. | G25: Blocks EP-07-S07 and EP-15-S04 Done calls. If EA has own login, Anthony needs to add a sixth user class -- significant backend scope.
A26: PA Resolution | B26: PA-72 -- Personal Information Inventory editability confirmed | C26: Ms. Mys | D26: 1 | E26: To Do | F26: Ms. Mys confirms whether PII Inventory is read-only report view or editable and annotatable by PMCM Admin. | G26: Blocks AC item 5 finalization in EP-15-S02. Story is live but AC placeholder remains.
A27: PA Resolution | B27: PA-73 -- ZDR agreement with Anthropic confirmed | C27: Anthony | D27: 1 | E27: To Do | F27: Anthony confirms in writing that ZDR agreement is secured with Anthropic. If not yet secured, contact api@anthropic.com immediately -- 1 to 3 business day setup window applies. | G27: CRITICAL. Gates all 10 AI features and EP-12-S02. Most urgent single action in the entire project. Cannot carry into C3.
A28: KEY ACTIONS -- Non-story tasks from C1
A29: Key Action | B29: Verify EP-18-S01 carry-over plan | C29: A (Maxine) | D29: 1 | E29: To Do | F29: Maxine confirms in writing or on ClickUp that EP-18-S01 will be Done within the first 3 days of C2. | G29: EP-18-S01 was In Progress at C1 close. All portal UI work downstream carries rework risk until it is Done.
A30: Key Action | B30: Retrospective PA audit -- confirm all C1 PAs above have owners and deadlines | C30: B (Francis) | D30: 1 | E30: To Do | F30: All C1 PAs above have a named resolver and a deadline documented on ClickUp or equivalent. | G30: PA-62, PA-69, PA-71, PA-72, PA-73 -- all must have owners assigned and deadlines set before C2 mid-point.
A31: Key Action | B31: Confirm EP-07-S07 Done call validity -- PA-71 check | C31: B (Francis) | D31: 1 | E31: To Do | F31: Francis confirms with Ms. Mys that EP-07-S07 Done call is valid despite PA-71 being open, or reverts story to In Review. | G31: If Ms. Mys confirms EA is a sub-role under PMCM Admin, Done call stands. If EA needs own login, revert and add backend auth scope.
A32: Key Action | B32: Confirm EP-15-S01 and EP-15-S02 Done call validity -- PA-69 and PA-72 check | C32: D (Anthony) | D32: 1 | E32: To Do | F32: Anthony confirms both stories are functionally complete despite open AC placeholders, and documents that PA-69 and PA-72 are retrospective AC finalization tasks only. | G32: Both stories are live. PAs affect only specific AC item text, not the implemented behavior.
A33: RED FLAGS -- Conditions signaling C1 retrospective is incomplete
A34: RED FLAG: EP-15-S05 (ZDR gate) is still To Do with no Anthropic contact initiated -- escalate to Anthony immediately. Every day of delay compresses C3 AI story delivery.
A35: RED FLAG: EP-18-S01 is still In Progress entering C2 with no confirmed close date from Maxine -- all portal UI work is at risk.
A36: RED FLAG: PA-71 (EA role) is unresolved and EA is confirmed to need own system login -- Anthony needs to add a sixth user class immediately; this is late-stage backend scope.
A37: RED FLAG: Any C1 story other than EP-18-S01 is not Done -- flag immediately on ClickUp and assign remediation owner before C2 day 3.
A38: C1 GATE CONDITIONS -- All must be true before C1 retrospective is considered closed
A39: GATE: All 13 C1 stories are Done except EP-18-S01 which is In Progress with a confirmed C2 close date from Maxine.
A40: GATE: PA-73 (ZDR) has been raised with Anthony and a response or action is on record.
A41: GATE: PA-71, PA-72, PA-62, PA-69 all have named resolvers and deadlines documented.
A42: GATE: EP-07-S07, EP-15-S01, EP-15-S02 Done calls are confirmed valid despite open PA placeholders.
A43: GATE: EP-18-S01 carry-over plan is confirmed and documented by Maxine.
A44: C1 Completion % | D44: =IFERROR((SUMPRODUCT((E8:E43="Done")*(D8:D43))+SUMPRODUCT((E8:E43="In Progress")*(D8:D43)*0.5))/SUMPRODUCT((D8:D43>0)*(D8:D43)),0) -> 0.72972973 | E44: Stories = weight 2 | PA resolutions, actions, owner tasks, gate conditions = weight 1
A47: C2 -- Cadence 2 First-Slice Delivery | June 22 - July 3, 2026 | Status: ACTIVE
A48: C2 is active now (June 26, 2026). EP-04-S01 (Conforme Gate) is the single most critical delivery -- it gates 19 downstream stories. EP-15-S05 (ZDR) must also be resolved before C2 closes or all AI stories are lost.
A49: Type | B49: Item / Description | C49: Owner | D49: Weight | E49: Status | F49: Done Criteria | G49: Notes / Context
A50: STORIES -- Must be Done by July 3, 2026
A51: Story | B51: EP-04-S01 -- Conforme upload -- atomic activation of client portal, billing, and event workspace | C51: B (Francis) | D51: 2 | E51: Done | F51: Non-PDF uploads rejected, atomic activation of all three workspaces on upload, rollback on failure, conforme stored and retrievable, audit log entry recorded, PA-109 resolved before Done call. | G51: HIGHEST PRIORITY C2 DELIVERY. Not yet started as of June 26. Gates 19 downstream stories across EP-03, EP-05, EP-06, EP-08, EP-09, EP-10, EP-11, EP-12, EP-13. Start immediately.
A52: Story | B52: EP-02-S02 -- Command inbox error state -- no false all-clear on fetch failure | C52: B (Francis) | D52: 2 | E52: Done | F52: Fetch failure renders a visible error state distinct from empty state. No false all-clear exists in any code path. Recovery from error transitions cleanly to loaded or empty state. | G52: RESOLVED. Commit e0f99c0. Amber AlertTriangle + '!' badge. Verified in Docker. FL-017 deferred item 1 complete.
A53: Story | B53: EP-02-S03 -- Command inbox item click-through navigation to event workspace | C53: B (Francis) | D53: 2 | E53: Done | F53: Each inbox item clickable and routes to correct event workspace section. Stale item click shows clear message. Non-PMCM actors cannot access click-through routes. | G53: RESOLVED. Commit a97498f. Conditional Link wrapping on item.href. Verified in Docker. T03 scope gap -- non-issue. FL-017 deferred item 2 complete.
A54: Story | B54: EP-02-S04 -- Command inbox mounted in final approved location per T03 design | C54: B (Francis) | D54: 2 | E54: Done | F54: RESOLVED as non-issue. Standalone route is correct per team plan. t03-acceptance-notes.md was AI-generated and never approved. No code change needed. Delete t03-acceptance-notes.md from Claude Code memory in next session. | G54: RESOLVED as non-issue. FL-017 deferred item 3 complete. PR #4 open on GitHub, ready for review.
A55: Story | B55: EP-02-S05 -- PMCM coordinator directory and assignment commands | C55: B (Francis) | D55: 2 | E55: To Do | F55: Full coordinator directory visible in apps/event, double-booking warning present and undismissable without explicit confirmation, Pending Acknowledgment status shown after assignment, same_tx pattern used, non-PMCM actors denied. | G55: Second highest C2 priority after EP-04-S01. Gates all five EP-11 coordinator stories in C3. Start after EP-04-S01 is In Progress.
A56: Story | B56: EP-03-S01 -- Event briefing creation and client submission | C56: B (Francis) | D56: 2 | E56: To Do | F56: Briefing creatable only after conforme signed, all five briefing sections captured, client receives briefing in portal, PMCM notified on client submission, briefing status trackable. | G56: Gated on EP-04-S01 Done. Cannot start until conforme is live.
A57: Story | B57: EP-03-S02 -- Proposal generation and client response | C57: B (Francis) | D57: 2 | E57: To Do | F57: Proposal generatable only after briefing complete, all five proposal sections present, client can accept or request revision, proposal history stored, conforme upload gated on proposal acceptance. | G57: Gated on EP-03-S01 Done. Manual proposal workflow only -- AI draft (EP-16-S02) is Phase 2 scope.
A58: Story | B58: EP-05-S01 -- Official floor plan creation and publication | C58: B (Francis) | D58: 2 | E58: To Do | F58: Floor plan creatable only after conforme signed, only PMCM Admin and system actors can mutate official state, published snapshot stored and retrievable, FLOORPLAN_COMMANDS port used for all writes, ocular visit gate confirmed with PA-59 resolution. | G58: Gated on EP-04-S01 Done. PA-59 override path must be confirmed with Ms. Mys before Done call.
A59: Story | B59: EP-05-S02 -- Client venue and layout preference submission | C59: C (Ethan) | D59: 2 | E59: To Do | F59: Client can submit preferences only after conforme signed, preference clearly labeled as draft not official floor plan, client cannot mutate official floor plan state, preference visible to PMCM Admin only. | G59: Gated on EP-04-S01 and EP-05-S01 Done.
A60: Story | B60: EP-05-S03 -- Client read-only approved floor plan view with revision comments | C60: C (Ethan) | D60: 2 | E60: To Do | F60: Client view is read-only, only primary client contact can submit revision comments, floor plan locked after PMCM Admin approval, non-client non-PMCM actors denied. | G60: Gated on EP-05-S01 Done.
A61: Story | B61: EP-05-S04 -- Floor plan canvas editor with draggable element library | C61: B (Francis) | D61: 2 | E61: To Do | F61: Canvas editor accessible to PMCM Admin only, pre-built elements library present by category, canvas persistence behavior unchanged from pre-extraction, sub-ticket hard dependency enforced. | G61: No upstream dependency but styling sub-tickets are blocked until EP-05-S01 (floor plan approval) is Done.
A62: Story | B62: EP-07-S06 -- Public supplier registration form | C62: C (Ethan) | D62: 2 | E62: To Do | F62: Form accessible without login, BNI Member toggle present and stored, submitted application routed to PMCM Admin inbox (EP-07-S09), application not auto-approved, PA-74 canonical FR number confirmed before Done call. | G62: PA-74 OPEN -- canonical FR number for New-SUP3/New-EX1/New-S1 must be confirmed before Done call.
... A70: Story | B70: EP-15-S05 -- ZDR confirmed and DataSanitizer enforced -- CRITICAL GATE | C70: D (Anthony) | D70: 2 | E70: To Do | F70: ZDR agreement with Anthropic documented in writing before any EP-16 story moves to In Progress. DataSanitizer implemented and tested. AIAuditLog table receives entries for every Claude API call. Human approval gate implemented as reusable component. | G70: CADENCE-DISPLACED FROM C1. Cannot carry into C3. Contact api@anthropic.com immediately if not yet initiated. 1 to 3 business day setup window. Gates all 10 AI features and EP-12-S02 and EP-12-S06.
A71: PA RESOLUTIONS -- Must be confirmed during C2
A72: PA Resolution | B72: PA-59 -- PMCM Admin override path for ocular visit gate | C72: Francis + Ms. Mys | D72: 1 | E72: To Do | F72: Ms. Mys confirms in writing or verbally: if client never completes ocular visit, can PMCM Admin override the gate and proceed to floor plan creation? Confirm the mechanism. | G72: Ask Ms. Mys: If a client never completes the ocular visit request, can PMCM Admin override the gate and proceed to floor plan creation anyway? Blocks EP-10-S03 In Review and EP-05-S01 Done call.
A73: PA Resolution | B73: PA-73 -- ZDR agreement status with Anthropic | C73: Anthony | D73: 1 | E73: To Do | F73: Anthony confirms in writing that ZDR is secured OR confirms that contact with api@anthropic.com has been initiated and provides expected confirmation date. | G73: MOST URGENT ACTION IN THE ENTIRE PROJECT. If not resolved by C2 close, all C3 and C4 AI stories must be declared post-July.
A74: PA Resolution | B74: PA-74 -- Canonical FR number for New-SUP3/New-EX1/New-S1 supplier registration | C74: Team | D74: 1 | E74: To Do | F74: Team agrees on one canonical FR number and name for the public supplier registration feature. Only one tracker story exists for this feature regardless of naming. | G74: Blocks EP-07-S06 Done call. Three names in source docs for one feature -- must be collapsed to one canonical ID.
A75: PA Resolution | B75: PA-76 -- Who performs Verified status on supplier on-site updates | C75: Ms. Mys | D75: 1 | E75: To Do | F75: Ms. Mys confirms which role performs the Verified status level on supplier status updates and through which portal surface they do it. | G75: Ask Ms. Mys: When a supplier marks themselves as Arrived or Set Up and Ready, who verifies that status and upgrades it from Self-Reported to Verified? Which app do they use? Blocks EP-07-S05 Done call.
A76: PA Resolution | B76: PA-109 -- uploadConforme billing path routing | C76: Anthony | D76: 1 | E76: To Do | F76: Anthony confirms in writing whether uploadConforme calls billing logic directly or routes through FinanceOpsModule. | G76: Blocks EP-04-S01 and EP-08-S01 Done calls. Must be resolved before either story can be called Done even if build is complete.
A77: PA Resolution | B77: PA-101 -- BILLING_READER and PAYMENT_STATUS_READER token implementations | C77: Anthony | D77: 1 | E77: To Do | F77: Anthony implements concrete implementations for both tokens and confirms on ClickUp. No cadence slot currently assigned -- must be slotted in C2 or early C3. | G77: Blocks EP-08-S02 In Review in C3. Must be implemented before EP-08-S02 build starts.
A78: PA Resolution | B78: PA-70 -- Per-type or global file size limits for uploads | C78: Anthony | D78: 1 | E78: To Do | F78: Anthony confirms whether file size limits are per file type or a single global limit, and states the specific values. | G78: Blocks AC item 4 finalization in EP-09-S02 and EP-15-S03 Phase 2 scope. Must be confirmed before EP-09-S02 Done call in C3.
A79: KEY ACTIONS -- Non-story tasks for C2
A80: Key Action | B80: Start EP-04-S01 build immediately | C80: B (Francis) | D80: 1 | E80: To Do | F80: Francis has started building EP-04-S01 in apps/event. Evidence: ClickUp card moved to In Progress. | G80: Not yet started as of June 26. Every day of delay compresses the 19 downstream stories.
A81: Key Action | B81: Contact api@anthropic.com for ZDR agreement | C81: D (Anthony) | D81: 1 | E81: To Do | F81: Email sent to api@anthropic.com and confirmation received or expected date documented. | G81: 1 to 3 business day setup window. Must be initiated immediately. Do not wait for C2 mid-point.
A82: Key Action | B82: Raise PA-109 with Anthony -- uploadConforme billing path | C82: B (Francis) | D82: 1 | E82: To Do | F82: Francis has explicitly asked Anthony to confirm the uploadConforme billing path. Anthony has responded or has a response deadline. | G82: Both EP-04-S01 and EP-08-S01 Done calls are blocked without this answer.
A83: Key Action | B83: Slot PA-101 implementation into Anthony C2 or early C3 workload | C83: D (Anthony) | D83: 1 | E83: To Do | F83: Anthony has added BILLING_READER and PAYMENT_STATUS_READER implementation to his ClickUp board with a target date. | G83: No cadence slot currently assigned. EP-08-S02 (C3 Must story) cannot reach In Review without these.
A84: Key Action | B84: Resolve Docker setup and branch merge blocker for EP-02-S02 through EP-02-S04 | C84: B (Francis) + Team | D84: 1 | E84: Done | F84: Docker Desktop installed and confirmed working. .env.docker set up. All three FL-017 deferred items resolved. EP-02-S02, EP-02-S03, and EP-02-S04 are all Done. | G84: COMPLETED. Docker working. .env.docker set up with Supabase values. Critical lesson: hot reload unreliable for EventDashboardClient.tsx -- always do full docker compose down then up --build api event.
A85: Key Action | B85: Maxine closes EP-18-S01 within first 3 days of C2 | C85: A (Maxine) | D85: 1 | E85: In Progress | F85: EP-18-S01 status on Tracker is Done. Maxine route-review log has at least one entry per portal. | G85: If EP-18-S01 is not Done by June 25, flag immediately. All portal UI work downstream is at rework risk.
A86: Key Action | B86: Confirm PA-59 ocular visit override with Ms. Mys | C86: B (Francis) | D86: 1 | E86: To Do | F86: Ms. Mys has confirmed whether PMCM Admin can override the ocular visit gate. Mechanism is documented. | G86: Needed before EP-10-S03 moves to In Review and before EP-05-S01 Done call.
A87: Key Action | B87: Confirm PA-76 Verified status actor with Ms. Mys | C87: B (Francis) | D87: 1 | E87: To Do | F87: Ms. Mys has confirmed which role performs Verified status level and through which surface. | G87: Needed before EP-07-S05 Done call.
A88: Key Action | B88: Confirm PA-71 EA role definition with Ms. Mys | C88: B (Francis) | D88: 1 | E88: To Do | F88: Ms. Mys has confirmed EA full role name and whether EA has own login or is sub-role under PMCM Admin. Anthony alerted if own login confirmed. | G88: Needed before EP-07-S07 and EP-15-S04 Done calls. If EA needs own login, Anthony must add sixth user class.
A89: OWNER TASKS -- Per-owner C2 delivery summary
A90: Owner Task | B90: Close EP-18-S01 (first 3 days of C2). Then EP-18-S02. Review EP-10-S01 against design system before Ethan calls Done. | C90: A (Maxine) | D90: 1 | E90: To Do | F90: EP-18-S01 Done, EP-18-S02 Done or In Progress, EP-10-S01 reviewed by Maxine before Done. | G90: 2 stories. Maxine has lightest load but EP-18-S01 is a foundation dependency for all portal work.
A91: Owner Task | B91: EP-04-S01 first (start immediately). Then EP-02-S05. Then EP-03-S01, EP-05-S01, EP-05-S04. EP-02-S02, EP-02-S03, and EP-02-S04 are all Done. FL-017 is fully complete. PR #4 open on GitHub, ready for review -- merge to main. | C91: B (Francis) | D91: 1 | E91: To Do | F91: EP-04-S01 Done by June 30. EP-02-S05 Done or In Progress by July 1. EP-03-S01 and EP-05-S01 In Progress by July 3. | G91: 8 stories this cadence. Heaviest C2 load. EP-04-S01 is non-negotiable first priority.
A92: Owner Task | B92: EP-05-S02, EP-05-S03, EP-07-S06, EP-10-S01 (remove fallback), EP-10-S03. Coordinate with Francis on floor plan sequence. | C92: C (Ethan) | D92: 1 | E92: To Do | F92: EP-10-S01 fallback removed and Done. EP-05-S02 and EP-05-S03 In Progress by July 1 (gated on Francis EP-04-S01 and EP-05-S01). | G92: 4 stories this cadence. EP-05-S02 and EP-05-S03 cannot start until Francis delivers EP-04-S01 and EP-05-S01.
A93: Owner Task | B93: EP-08-S01, EP-09-S01, EP-15-S03, EP-15-S05 (ZDR -- URGENT). Resolve PA-109 and PA-101. Slot PA-101 implementation. | C93: D (Anthony) | D93: 1 | E93: To Do | F93: EP-15-S05 Done or ZDR contact confirmed. EP-08-S01 and EP-09-S01 In Progress by July 1. PA-109 resolved by June 28. | G93: 4 stories plus ZDR gate. EP-15-S05 is the most critical deliverable regardless of story count.
A94: RED FLAGS -- Conditions signaling C2 is at risk
A95: RED FLAG: EP-04-S01 not Done by June 30 -- immediate escalation to full team. 19 downstream stories cannot close. C3 delivery is unachievable.
A96: RED FLAG: EP-15-S05 still To Do with no Anthropic contact by June 28 -- all C3 and C4 AI stories must be pre-emptively declared post-July.
A97: RED FLAG: EP-02-S05 not Done by July 1 -- all five EP-11 coordinator stories in C3 cannot start. Coordinator experience epic is undeliverable.
A98: RED FLAG: EP-18-S01 not Done by June 25 -- Maxine must flag immediately. All portal UI consistency is at risk.
A99: RED FLAG: PA-109 unresolved by June 28 -- EP-04-S01 and EP-08-S01 Done calls are blocked even if builds are complete.
A100: RESOLVED: Docker setup and branch merges are complete. EP-02-S02, EP-02-S03, and EP-02-S04 are all Done. FL-017 is fully complete.
A101: RED FLAG: EP-10-S01 fallback derivation logic still present at C2 close -- story cannot be called Done.
A102: C2 GATE CONDITIONS -- All must be true before moving to C3
A103: GATE: EP-04-S01 is Done. This is non-negotiable -- no exceptions.
A104: GATE: EP-15-S05 is Done OR ZDR contact with Anthropic is confirmed and expected resolution date is documented.
A105: GATE: EP-02-S05 is Done or In Review.
... A111: GATE: ClickUp board reflects actual status -- no story is Done on the board without evidence.
A112: C2 Completion % | D112: =IFERROR((SUMPRODUCT((E51:E111="Done")*(D51:D111))+SUMPRODUCT((E51:E111="In Progress")*(D51:D111)*0.5))/SUMPRODUCT((D51:D111>0)*(D51:D111)),0) -> 0.19166667 | E112: Stories = weight 2 | PA resolutions, actions, owner tasks, gate conditions = weight 1
A115: C3 -- Cadence 3 Workflow Completion | July 6-17, 2026 | Feature Freeze at Close
A116: C3 is the most loaded cadence. Feature freeze at July 17 close -- after this date only release-blocker fixes, verification failures, documentation, small UX clarity fixes, and approved gate documentation are permitted. First actions at C3 start are mandatory before any story work begins.
A117: Type | B117: Item / Description | C117: Owner | D117: Weight | E117: Status | F117: Done Criteria | G117: Notes / Context
A118: MANDATORY FIRST ACTIONS -- Must happen on July 6 before any story work begins
...

Sheet AC Detail
A1: AC Detail Tab -- Populated only when EP-11-S05 break-down trigger fires or when instructed
A2: Story ID | B2: Role View / Criterion | C2: AC Item # | D2: AC Description | E2: Status | F2: Owner | G2: Notes
A3: EP-11-S05 -- Coordinator Role Views (Break-Down Trigger Active)
A4: Populated when any single role view reaches Done while others are still In Progress or Blocked. Track each role view independently below.
A5: EP-11-S05 RV1 | B5: Floor Director and Stage Director (New-CO2) | D5: 1. Role badge, event details, briefing documents, and assigned task list displayed. 2. Communication thread scoped exclusively to Event Day System Operator and Ms. Mys. 3. No other coordinator role, client, supplier, or guest actor can access this view. 4. Coordinator assigned to different role cannot access this view. | E5: To Do | F5: B (Francis) | G5: Build sequence: 3rd. Shared elements (role badge, event details header) from packages/ui.
A6: EP-11-S05 RV2 | B6: Registration Staff (New-CO3) | D6: 1. Role view laptop-optimized for desktop use. 2. Searchable guest masterlist with Check In button per guest row. 3. Walk-In Addition button present; record added to masterlist immediately. 4. Flag for Verification control present; flagged records visually distinguished. 5. Real-time attendance count visible and updates without manual refresh. 6. No client, supplier, or guest actor can access this view. | E6: To Do | F6: B (Francis) | G6: Build sequence: 2nd. Feeds EP-13-S01 directly. Shared elements from packages/ui.
A7: EP-11-S05 RV3 | B7: Ingress and Egress Assistant (New-CO4) | D7: 1. Role badge, supplier schedule, and exactly three status buttons per supplier: Arrived, Set Up and Ready, Done and Leaving. 2. Verified toggle and optional photo upload per status update present and functional. 3. Late Arrival flag appears at exactly 15 minutes past scheduled supplier window; not before. 4. No client, supplier, or guest actor can access this view. | E7: To Do | F7: B (Francis) | G7: Build sequence: 4th. 15-minute threshold is exact. Shared elements from packages/ui.
A8: EP-11-S05 RV4 | B8: Event Day System Operator (New-CO5) | D8: 1. Displays on laptop: full event task dashboard, supplier status overview, coordinator check-in section, urgent issue log one-tap access, task reassignment tool, wrap-up screen access, real-time attendance feed. 2. Task reassignment notifies Ms. Mys; auto-approval fires after exactly 2 minutes if no response. 3. Auto-approval recorded with timestamp and reason. 4. No client, supplier, or guest actor can access this view. | E8: To Do | F8: B (Francis) | G8: Build sequence: 1st (most complex; gates EP-12-S04). Coordinate with Anthony on notification-ops before In Review. Shared elements from packages/ui.
A9: EP-11-S05 RV5 | B9: Usher and General Coordinator (New-CO6) | D9: 1. Displays: role badge, simple instruction list with post and responsibilities, urgent issue button only. 2. No task management controls, coordinator directory data, or supplier information visible. 3. Interface minimal beyond role badge, instruction list, and urgent issue button. 4. No client, supplier, or guest actor can access this view. | E9: To Do | F9: B (Francis) | G9: Build sequence: 5th (simplest). Shared elements from packages/ui.
A11: Cross-Role Rules (apply to all role views)
A12: 1. Each coordinator only sees the role view matching their assigned role; a Registration Staff coordinator cannot access the Event Day System Operator view.
A13: 2. Client, supplier, and guest actors cannot access any coordinator role view under any circumstance.
A14: 3. Break-down trigger monitored at every cadence boundary; if any single role view Done while others stuck, update this tab immediately.
A15: 4. Shared UI elements (role badge, urgent issue button, event details header) extracted to packages/ui before any individual role view is built.

Sheet Cadence Review Guide
A1: P.R.I.S.M. AC Tracker -- Cadence Review Guide
A2: Google Sheets Tab Reference | Phase 3 Output | Produced: June 26, 2026 | Team CG | University of Santo Tomas
A4: STANDING RULES (ALL CADENCES)
A5: 1. Child plan task checkboxes are authoritative. Master plan checkboxes and Implementation Status claims are not sufficient for a Done call.
A6: 2. No story moves to Done without at least one other owner reviewing.
A7: 3. No AI story moves to In Progress without EP-15-S05 (ZDR) confirmed Done.
A8: 4. No upload session, signed URL, or real file persistence without Anthony explicit approval.
A9: 5. No sprint or Scrum language anywhere -- including review notes, ClickUp cards, and verbal status updates.
A10: 6. EP-11-S05 break-down trigger: if any single coordinator role view story reaches Done while other role views are stuck, move EP-11-S05 to AC Detail tab immediately.
A11: 7. When in doubt about a Done call, the answer is In Review until evidence exists.
A12: 8. Blocked status is used for stories with unmet gate conditions, unresolved PAs blocking AC items, or hard-gated dependencies. Not Started is not used for gated items.
A13: 9. Role-boundary scan (DoD criterion C) must be completed before Done is called on any story. Notes-only gate conditions D, N, O, P are verified in the same pass as C.
... A71: PA-131 | EP-17-S02 | Anthony | Before EP-17-S02 Done (C3) | event-ops-client.ts rename decision.
